Workbook
Name UPDATE: 'data sheet'!$E$1

Sheet Front page
B10: TATA STEEL LTD
B11: BSE: 500470
B12: NSE: TATA STEEL
B19: Financial Modelling
G20: Report
B24: ( A Comprehensive DCF & Comparable Comps Valuation )
F36: Prepared by : Akanksha Singh

Sheet Contents list
C2: Table of Contents
A4: 1 | B4: Historical Financial Statement
A5: =1+A4 -> 2 | B5: Common Size Statement
A6: =1+A5 -> 3 | B6: Ratio Analysis
A7: =1+A6 -> 4 | B7: Forecasting
A8: =1+A7 -> 5 | B8: Regression Beta
A9: =1+A8 -> 6 | B9: Return on Market
A10: =1+A9 -> 7 | B10: Weighted Average Cost of Capital (WACC)
A11: =1+A10 -> 8 | B11: Intrinsic Growth
A12: =1+A11 -> 9 | B12: DCF Valuation
A13: =1+A12 -> 10 | B13: Comparable Copanies Valuation
A14: =1+A13 -> 11 | B14: Sensitivity Analysis
A15: =1+A14 -> 12 | B15: Football Field Analysis

Sheet HISTORICAL(FS)
B2: Historical Financial Statement- TATA STEEL LTD
B3: Years | C3: =IFERROR('data sheet'!B16,0) -> 42460 | D3: =IFERROR('data sheet'!C16,0) -> 42825 | E3: =IFERROR('data sheet'!D16,0) -> 43190 | F3: =IFERROR('data sheet'!E16,0) -> 43555 | G3: =IFERROR('data sheet'!F16,0) -> 43921 | H3: =IFERROR('data sheet'!G16,0) -> 44286 | I3: =IFERROR('data sheet'!H16,0) -> 44651 | J3: =IFERROR('data sheet'!I16,0) -> 45016 | ... L3: =IFERROR('data sheet'!K16,0) -> 45747 | M3: LTM
A5: # | B5: Income Statement
B7: Sales | C7: =IFERROR('data sheet'!B17,0) -> 101964.72 | D7: =IFERROR('data sheet'!C17,0) -> 112299.42 | E7: =IFERROR('data sheet'!D17,0) -> 123249.07 | F7: =IFERROR('data sheet'!E17,0) -> 157668.99 | G7: =IFERROR('data sheet'!F17,0) -> 139816.65 | H7: =IFERROR('data sheet'!G17,0) -> 156477.4 | I7: =IFERROR('data sheet'!H17,0) -> 243959.17 | J7: =IFERROR('data sheet'!I17,0) -> 243352.69 | ... L7: =IFERROR('data sheet'!K17,0) -> 218542.51 | M7: =IFERROR(SUM('data sheet'!H41:K41),0) -> 225087.92
B8: Sales Growth | C8: - | D8: =D7/C7-1 -> 0.10135565 | E8: =E7/D7-1 -> 0.097504065 | F8: =F7/E7-1 -> 0.27927124 | G8: =G7/F7-1 -> -0.1132267 | H8: =H7/G7-1 -> 0.11916142 | I8: =I7/H7-1 -> 0.55906968 | J8: =J7/I7-1 -> -0.0024859898 | K8: =K7/J7-1 -> -0.058277186 | ... M8: =M7/L7-1 -> 0.029950283
B10: COGS | C10: =IFERROR(SUM('data sheet'!B18,'data sheet'!B20:B22)-1*'data sheet'!B19,0) -> 79237.26 | D10: =IFERROR(SUM('data sheet'!C18,'data sheet'!C20:C22)-1*'data sheet'!C19,0) -> 77577.09 | E10: =IFERROR(SUM('data sheet'!D18,'data sheet'!D20:D22)-1*'data sheet'!D19,0) -> 84710.05 | F10: =IFERROR(SUM('data sheet'!E18,'data sheet'!E20:E22)-1*'data sheet'!E19,0) -> 105590.05 | G10: =IFERROR(SUM('data sheet'!F18,'data sheet'!F20:F22)-1*'data sheet'!F19,0) -> 102560.94 | H10: =IFERROR(SUM('data sheet'!G18,'data sheet'!G20:G22)-1*'data sheet'!G19,0) -> 102979.74 | I10: =IFERROR(SUM('data sheet'!H18,'data sheet'!H20:H22)-1*'data sheet'!H19,0) -> 143605.19 | J10: =IFERROR(SUM('data sheet'!I18,'data sheet'!I20:I22)-1*'data sheet'!I19,0) -> 178329.36 | ... L10: =IFERROR(SUM('data sheet'!K18,'data sheet'!K20:K22)-1*'data sheet'!K19,0) -> 171714.99 | M10: =IFERROR(SUM('data sheet'!H42:K42),0) -> 194004.92
B11: COGS % Sales | C11: =C10/C7 -> 0.77710467 | D11: =D10/D7 -> 0.69080579 | E11: =E10/E7 -> 0.68730782 | F11: =F10/F7 -> 0.66969447 | G11: =G10/G7 -> 0.73353882 | H11: =H10/H7 -> 0.65811255 | I11: =I10/I7 -> 0.58864436 | J11: =J10/J7 -> 0.73280209 | ... M11: =M10/M7 -> 0.86190729
B13: Gross Profit | C13: =C7-'HISTORICAL(FS)'!C10 -> 22727.46 | D13: =D7-'HISTORICAL(FS)'!D10 -> 34722.33 | E13: =E7-'HISTORICAL(FS)'!E10 -> 38539.02 | F13: =F7-'HISTORICAL(FS)'!F10 -> 52078.94 | G13: =G7-'HISTORICAL(FS)'!G10 -> 37255.71 | H13: =H7-'HISTORICAL(FS)'!H10 -> 53497.66 | I13: =I7-'HISTORICAL(FS)'!I10 -> 100353.98 | J13: =J7-'HISTORICAL(FS)'!J10 -> 65023.33 | ... M13: =M7-'HISTORICAL(FS)'!M10 -> 31083
B14: Gross Margins | C14: =C13/C7 -> 0.22289533 | D14: =D13/D7 -> 0.30919421 | E14: =E13/E7 -> 0.31269218 | F14: =F13/F7 -> 0.33030553 | G14: =G13/G7 -> 0.26646118 | H14: =H13/H7 -> 0.34188745 | I14: =I13/I7 -> 0.41135564 | J14: =J13/J7 -> 0.26719791 | ... M14: =M13/M7 -> 0.13809271
B16: Selling & General Expenses | C16: =IFERROR(SUM('data sheet'!B23:B24),0) -> 23352.7 | D16: =IFERROR(SUM('data sheet'!C23:C24),0) -> 21578.7 | E16: =IFERROR(SUM('data sheet'!D23:D24),0) -> 17105.83 | F16: =IFERROR(SUM('data sheet'!E23:E24),0) -> 22760.72 | G16: =IFERROR(SUM('data sheet'!F23:F24),0) -> 19792.65 | H16: =IFERROR(SUM('data sheet'!G23:G24),0) -> 22993.4 | I16: =IFERROR(SUM('data sheet'!H23:H24),0) -> 36864.03 | J16: =IFERROR(SUM('data sheet'!I23:I24),0) -> 32723.17 | ... L16: =IFERROR(SUM('data sheet'!K23:K24),0) -> 21529.07
B17: S&G Exp % Sales | C17: =C16/C7 -> 0.22902726 | D17: =D16/D7 -> 0.19215326 | E17: =E16/E7 -> 0.13879074 | F17: =F16/F7 -> 0.14435762 | G17: =G16/G7 -> 0.14156147 | H17: =H16/H7 -> 0.1469439 | I17: =I16/I7 -> 0.15110738 | J17: =J16/J7 -> 0.13446808 | ... M17: =M16/M7 -> 0
B19: EBITDA | C19: =IFERROR(C13-C16,0) -> -625.24 | D19: =IFERROR(D13-D16,0) -> 13143.63 | E19: =IFERROR(E13-E16,0) -> 21433.19 | F19: =IFERROR(F13-F16,0) -> 29318.22 | G19: =IFERROR(G13-G16,0) -> 17463.06 | H19: =IFERROR(H13-H16,0) -> 30504.26 | I19: =IFERROR(I13-I16,0) -> 63489.95 | J19: =IFERROR(J13-J16,0) -> 32300.16 | ... L19: =IFERROR(L13-L16,0) -> 25298.45 | M19: =IFERROR(SUM('data sheet'!H51:K51),0) -> 31974.76
B20: EBITDA Margins | C20: =C19/C7 -> -0.0061319248 | D20: =D19/D7 -> 0.11704094 | E20: =E19/E7 -> 0.17390143 | F20: =F19/F7 -> 0.18594792 | G20: =G19/G7 -> 0.12489972 | H20: =H19/H7 -> 0.19494355 | I20: =I19/I7 -> 0.26024826 | J20: =J19/J7 -> 0.13272983 | ... M20: =M19/M7 -> 0.14205454
B22: Interest | C22: =IFERROR('data sheet'!B27,0) -> 4221.41 | D22: =IFERROR('data sheet'!C27,0) -> 5072.2 | E22: =IFERROR('data sheet'!D27,0) -> 5454.74 | F22: =IFERROR('data sheet'!E27,0) -> 7660.1 | G22: =IFERROR('data sheet'!F27,0) -> 7533.46 | H22: =IFERROR('data sheet'!G27,0) -> 7606.71 | I22: =IFERROR('data sheet'!H27,0) -> 5462.2 | J22: =IFERROR('data sheet'!I27,0) -> 6298.7 | ... M22: =IFERROR('data sheet'!L27,0) -> 0
B23: Interest % Sales | C23: =C22/C7 -> 0.041400692 | D23: =D22/D7 -> 0.045166752 | E23: =E22/E7 -> 0.044257859 | F23: =F22/F7 -> 0.048583428 | G23: =G22/G7 -> 0.053880993 | H23: =H22/H7 -> 0.048612196 | I23: =I22/I7 -> 0.022389812 | J23: =J22/J7 -> 0.02588301 | ... M23: =M22/M7 -> 0
B25: Depreciation | C25: =IFERROR('data sheet'!B26,0) -> 5306.35 | D25: =IFERROR('data sheet'!C26,0) -> 5672.88 | E25: =IFERROR('data sheet'!D26,0) -> 5741.7 | F25: =IFERROR('data sheet'!E26,0) -> 7341.83 | G25: =IFERROR('data sheet'!F26,0) -> 8440.73 | H25: =IFERROR('data sheet'!G26,0) -> 9233.64 | I25: =IFERROR('data sheet'!H26,0) -> 9100.87 | J25: =IFERROR('data sheet'!I26,0) -> 9335.2 | ... L25: =IFERROR('data sheet'!K26,0) -> 10421.33 | M25: =IFERROR(SUM('data sheet'!H44:K44),0) -> 11406.08
B26: Depreciation % Sales | C26: =C25/C7 -> 0.052041039 | D26: =D25/D7 -> 0.050515666 | E26: =E25/E7 -> 0.046586153 | F26: =F25/F7 -> 0.046564832 | G26: =G25/G7 -> 0.060369992 | H26: =H25/H7 -> 0.059009416 | I26: =I25/I7 -> 0.03730489 | J26: =J25/J7 -> 0.038360784 | ... M26: =M25/M7 -> 0.050673888
B28: Earnings before Tax | C28: =IFERROR(C19-SUM(C22,C25),0) -> -10153 | D28: =IFERROR(D19-SUM(D22,D25),0) -> 2398.55 | E28: =IFERROR(E19-SUM(E22,E25),0) -> 10236.75 | F28: =IFERROR(F19-SUM(F22,F25),0) -> 14316.29 | G28: =IFERROR(G19-SUM(G22,G25),0) -> 1488.87 | H28: =IFERROR(H19-SUM(H22,H25),0) -> 13663.91 | I28: =IFERROR(I19-SUM(I22,I25),0) -> 48926.88 | J28: =IFERROR(J19-SUM(J22,J25),0) -> 16666.26 | ... M28: =IFERROR(M19-SUM(M22,M25),0) -> 20568.68
B29: EBT % Sales | C29: =C28/C7 -> -0.099573656 | D29: =D28/D7 -> 0.021358525 | E29: =E28/E7 -> 0.083057422 | F29: =F28/F7 -> 0.090799656 | G29: =G28/G7 -> 0.010648732 | H29: =H28/H7 -> 0.087321939 | I29: =I28/I7 -> 0.20055356 | J29: =J28/J7 -> 0.068486032 | ... M29: =M28/M7 -> 0.091380648
B31: Tax | C31: =IFERROR('data sheet'!B29,0) -> 689.96 | D31: =IFERROR('data sheet'!C29,0) -> 2778.01 | E31: =IFERROR('data sheet'!D29,0) -> 3392.33 | F31: =IFERROR('data sheet'!E29,0) -> 6718.43 | G31: =IFERROR('data sheet'!F29,0) -> -2568.41 | H31: =IFERROR('data sheet'!G29,0) -> 5653.9 | I31: =IFERROR('data sheet'!H29,0) -> 8477.55 | J31: =IFERROR('data sheet'!I29,0) -> 10159.77 | ... L31: =IFERROR('data sheet'!K29,0) -> 5239.09 | M31: =IFERROR(SUM('data sheet'!H47:K47),0) -> 4236.31
B32: Effective Tax Rate | C32: =C31/C28 -> -0.067956269 | D32: =D31/D28 -> 1.1582039 | E32: =E31/E28 -> 0.3313874 | F32: =F31/F28 -> 0.46928569 | G32: =G31/G28 -> -1.7250734 | H32: =H31/H28 -> 0.41378346 | I32: =I31/I28 -> 0.17326979 | J32: =J31/J28 -> 0.60960107 | ... M32: =M31/M28 -> 0.20595925
B34: Net Profit | C34: =IFERROR(C28-C31,0) -> -10842.96 | D34: =IFERROR(D28-D31,0) -> -379.46 | E34: =IFERROR(E28-E31,0) -> 6844.42 | F34: =IFERROR(F28-F31,0) -> 7597.86 | G34: =IFERROR(G28-G31,0) -> 4057.28 | H34: =IFERROR(H28-H31,0) -> 8010.01 | I34: =IFERROR(I28-I31,0) -> 40449.33 | J34: =IFERROR(J28-J31,0) -> 6506.49 | ... M34: =IFERROR(M28-M31,0) -> 16332.37
B35: Net Margins | C35: =C34/C7 -> -0.10634031 | D35: =D34/D7 -> -0.0033790023 | E35: =E34/E7 -> 0.055533239 | F35: =F34/F7 -> 0.048188677 | G35: =G34/G7 -> 0.029018575 | H35: =H34/H7 -> 0.051189565 | I35: =I34/I7 -> 0.16580369 | J35: =J34/J7 -> 0.026736873 | ... M35: =M34/M7 -> 0.072559958
B37: No of Equity Shares | C37: =IFERROR('data sheet'!B93,0) -> 1126.62 | D37: =IFERROR('data sheet'!C93,0) -> 1126.62 | E37: =IFERROR('data sheet'!D93,0) -> 1126.48 | F37: =IFERROR('data sheet'!E93,0) -> 1126.49 | G37: =IFERROR('data sheet'!F93,0) -> 1126.49 | H37: =IFERROR('data sheet'!G93,0) -> 1196.59 | I37: =IFERROR('data sheet'!H93,0) -> 1221.3 | J37: =IFERROR('data sheet'!I93,0) -> 1222.15 | ... M37: =IFERROR('data sheet'!L93,0) -> 0
B39: Earning per Share | C39: =IFERROR(C34/C37,0) -> -9.6243276 | D39: =IFERROR(D34/D37,0) -> -0.33681277 | E39: =IFERROR(E34/E37,0) -> 6.0759357 | F39: =IFERROR(F34/F37,0) -> 6.7447203 | G39: =IFERROR(G34/G37,0) -> 3.6017009 | H39: =IFERROR(H34/H37,0) -> 6.6940305 | I39: =IFERROR(I34/I37,0) -> 33.119897 | J39: =IFERROR(J34/J37,0) -> 5.3238064 | ... M39: =IFERROR(M34/M37,0) -> 0
B40: EPS Growth % | D40: =IFERROR(D39/C39-1,0) -> -0.96500402 | E40: =IFERROR(E39/D39-1,0) -> -19.039505 | F40: =IFERROR(F39/E39-1,0) -> 0.11007106 | G40: =IFERROR(G39/F39-1,0) -> -0.465997 | H40: =IFERROR(H39/G39-1,0) -> 0.85857482 | I40: =IFERROR(I39/H39-1,0) -> 3.9476764 | J40: =IFERROR(J39/I39-1,0) -> -0.83925655 | K40: =IFERROR(K39/J39-1,0) -> -0.8351453 | ... M40: =IFERROR(M39/L39-1,0) -> -1
B42: Divident per Share | C42: =IFERROR('data sheet'!B31/'HISTORICAL(FS)'!C37,0) -> 0.68895457 | D42: =IFERROR('data sheet'!C31/'HISTORICAL(FS)'!D37,0) -> 0.86119543 | E42: =IFERROR('data sheet'!D31/'HISTORICAL(FS)'!E37,0) -> 1.0163962 | F42: =IFERROR('data sheet'!E31/'HISTORICAL(FS)'!F37,0) -> 1.32129 | G42: =IFERROR('data sheet'!F31/'HISTORICAL(FS)'!G37,0) -> 1.0163872 | H42: =IFERROR('data sheet'!G31/'HISTORICAL(FS)'!H37,0) -> 2.5021269 | I42: =IFERROR('data sheet'!H31/'HISTORICAL(FS)'!I37,0) -> 5.0996234 | J42: =IFERROR('data sheet'!I31/'HISTORICAL(FS)'!J37,0) -> 3.5973162 | ... M42: =IFERROR('data sheet'!L31/'HISTORICAL(FS)'!M37,0) -> 0
B43: Divident payout ratio | C43: =IFERROR(C42/C39,0) -> -0.071584696 | D43: =IFERROR(D42/D39,0) -> -2.5568966 | E43: =IFERROR(E42/E39,0) -> 0.16728225 | F43: =IFERROR(F42/F39,0) -> 0.1958999 | G43: =IFERROR(G42/G39,0) -> 0.28219645 | H43: =IFERROR(H42/H39,0) -> 0.3737848 | I43: =IFERROR(I42/I39,0) -> 0.15397461 | J43: =IFERROR(J42/J39,0) -> 0.6757038 | ... M43: =IFERROR(M42/M39,0) -> 0
B45: Retained Earnings | C45: =IFERROR(IF(C39>C42,1-C43,0),0) -> 0 | D45: =IFERROR(IF(D39>D42,1-D43,0),0) -> 0 | E45: =IFERROR(IF(E39>E42,1-E43,0),0) -> 0.83271775 | F45: =IFERROR(IF(F39>F42,1-F43,0),0) -> 0.8041001 | G45: =IFERROR(IF(G39>G42,1-G43,0),0) -> 0.71780355 | H45: =IFERROR(IF(H39>H42,1-H43,0),0) -> 0.6262152 | I45: =IFERROR(IF(I39>I42,1-I43,0),0) -> 0.84602539 | J45: =IFERROR(IF(J39>J42,1-J43,0),0) -> 0.3242962 | ... M45: =IFERROR(IF(M39>M42,1-M43,0),0) -> 0
A48: # | B48: Balance Sheet
B50: Equity Share Capital | C50: =IFERROR('data sheet'!B56,0) -> 970.24 | D50: =IFERROR('data sheet'!C56,0) -> 970.24 | E50: =IFERROR('data sheet'!D56,0) -> 1144.95 | F50: =IFERROR('data sheet'!E56,0) -> 1144.94 | G50: =IFERROR('data sheet'!F56,0) -> 1144.95 | H50: =IFERROR('data sheet'!G56,0) -> 1197.61 | I50: =IFERROR('data sheet'!H56,0) -> 1221.21 | J50: =IFERROR('data sheet'!I56,0) -> 1221.24 | ... L50: =IFERROR('data sheet'!K56,0) -> 1247.44
B51: Reserves | C51: =IFERROR('data sheet'!B57,0) -> 42762.31 | D51: =IFERROR('data sheet'!C57,0) -> 36849.08 | E51: =IFERROR('data sheet'!D57,0) -> 59725.67 | F51: =IFERROR('data sheet'!E57,0) -> 67780.14 | G51: =IFERROR('data sheet'!F57,0) -> 72431.35 | H51: =IFERROR('data sheet'!G57,0) -> 73041.16 | I51: =IFERROR('data sheet'!H57,0) -> 113221.83 | J51: =IFERROR('data sheet'!I57,0) -> 101860.86 | ... L51: =IFERROR('data sheet'!K57,0) -> 89922.19
B52: Borrowings | C52: =IFERROR('data sheet'!B58,0) -> 81986.93 | D52: =IFERROR('data sheet'!C58,0) -> 83014.49 | E52: =IFERROR('data sheet'!D58,0) -> 92147.05 | F52: =IFERROR('data sheet'!E58,0) -> 100816.22 | G52: =IFERROR('data sheet'!F58,0) -> 116328.2 | H52: =IFERROR('data sheet'!G58,0) -> 88501.41 | I52: =IFERROR('data sheet'!H58,0) -> 75561.35 | J52: =IFERROR('data sheet'!I58,0) -> 84893.05 | ... L52: =IFERROR('data sheet'!K58,0) -> 94801.05
B53: Other Liabilities | C53: =IFERROR('data sheet'!B59,0) -> 51164.51 | D53: =IFERROR('data sheet'!C59,0) -> 51613.56 | E53: =IFERROR('data sheet'!D59,0) -> 55704.47 | F53: =IFERROR('data sheet'!E59,0) -> 63032.14 | G53: =IFERROR('data sheet'!F59,0) -> 59244.62 | H53: =IFERROR('data sheet'!G59,0) -> 81169.01 | I53: =IFERROR('data sheet'!H59,0) -> 92417.28 | J53: =IFERROR('data sheet'!I59,0) -> 97420.63 | ... L53: =IFERROR('data sheet'!K59,0) -> 89487.9
B54: Total Liabilities | C54: =IFERROR('data sheet'!B60,0) -> 176883.99 | D54: =IFERROR('data sheet'!C60,0) -> 172447.37 | E54: =IFERROR('data sheet'!D60,0) -> 208722.14 | F54: =IFERROR('data sheet'!E60,0) -> 232773.44 | G54: =IFERROR('data sheet'!F60,0) -> 249149.12 | H54: =IFERROR('data sheet'!G60,0) -> 243909.19 | I54: =IFERROR('data sheet'!H60,0) -> 282421.67 | J54: =IFERROR('data sheet'!I60,0) -> 285395.78 | ... L54: =IFERROR('data sheet'!K60,0) -> 275458.58
B56: Fixed Assets Net Block | C56: =IFERROR('data sheet'!B61,0) -> 72199.76 | D56: =IFERROR('data sheet'!C61,0) -> 92006.55 | E56: =IFERROR('data sheet'!D61,0) -> 96104.89 | F56: =IFERROR('data sheet'!E61,0) -> 124441.91 | G56: =IFERROR('data sheet'!F61,0) -> 134550.66 | H56: =IFERROR('data sheet'!G61,0) -> 135775.18 | I56: =IFERROR('data sheet'!H61,0) -> 133287.83 | J56: =IFERROR('data sheet'!I61,0) -> 146621.46 | ... L56: =IFERROR('data sheet'!K61,0) -> 150914.06
B57: Capital Work in Progress | C57: =IFERROR('data sheet'!B62,0) -> 35996.09 | D57: =IFERROR('data sheet'!C62,0) -> 15784.13 | E57: =IFERROR('data sheet'!D62,0) -> 16614.41 | F57: =IFERROR('data sheet'!E62,0) -> 18641.21 | G57: =IFERROR('data sheet'!F62,0) -> 19496.83 | H57: =IFERROR('data sheet'!G62,0) -> 19007.4 | I57: =IFERROR('data sheet'!H62,0) -> 22045.55 | J57: =IFERROR('data sheet'!I62,0) -> 31213.02 | ... L57: =IFERROR('data sheet'!K62,0) -> 41622.35
B58: Investments | C58: =IFERROR('data sheet'!B63,0) -> 10713.71 | D58: =IFERROR('data sheet'!C63,0) -> 12457.12 | E58: =IFERROR('data sheet'!D63,0) -> 17899.47 | F58: =IFERROR('data sheet'!E63,0) -> 5738.17 | G58: =IFERROR('data sheet'!F63,0) -> 6285.18 | H58: =IFERROR('data sheet'!G63,0) -> 10681.93 | I58: =IFERROR('data sheet'!H63,0) -> 13139.85 | J58: =IFERROR('data sheet'!I63,0) -> 8410.31 | ... L58: =IFERROR('data sheet'!K63,0) -> 6194.11
B59: Other Assets | C59: =IFERROR('data sheet'!B64-SUM('data sheet'!B66:B68),0) -> 19708.54 | D59: =IFERROR('data sheet'!C64-SUM('data sheet'!C66:C68),0) -> 10887.88 | E59: =IFERROR('data sheet'!D64-SUM('data sheet'!D66:D68),0) -> 29418.96 | F59: =IFERROR('data sheet'!E64-SUM('data sheet'!E66:E68),0) -> 37143.68 | G59: =IFERROR('data sheet'!F64-SUM('data sheet'!F66:F68),0) -> 41808.1 | H59: =IFERROR('data sheet'!G64-SUM('data sheet'!G66:G68),0) -> 29846.28 | I59: =IFERROR('data sheet'!H64-SUM('data sheet'!H66:H68),0) -> 36978.69 | J59: =IFERROR('data sheet'!I64-SUM('data sheet'!I66:I68),0) -> 23121.16 | ... L59: =IFERROR('data sheet'!K64-SUM('data sheet'!K66:K68),0) -> 15231.08
B60: Total Non Current Assets | C60: =IFERROR(SUM(C56:C59),0) -> 138618.1 | D60: =IFERROR(SUM(D56:D59),0) -> 131135.68 | E60: =IFERROR(SUM(E56:E59),0) -> 160037.73 | F60: =IFERROR(SUM(F56:F59),0) -> 185964.97 | G60: =IFERROR(SUM(G56:G59),0) -> 202140.77 | H60: =IFERROR(SUM(H56:H59),0) -> 195310.79 | I60: =IFERROR(SUM(I56:I59),0) -> 205451.92 | J60: =IFERROR(SUM(J56:J59),0) -> 209365.95 | ... L60: =IFERROR(SUM(L56:L59),0) -> 213961.6
B62: Receivables | C62: =IFERROR('data sheet'!B66,0) -> 12066.22 | D62: =IFERROR('data sheet'!C66,0) -> 11586.82 | E62: =IFERROR('data sheet'!D66,0) -> 12415.52 | F62: =IFERROR('data sheet'!E66,0) -> 11811 | G62: =IFERROR('data sheet'!F66,0) -> 7884.91 | H62: =IFERROR('data sheet'!G66,0) -> 9539.84 | I62: =IFERROR('data sheet'!H66,0) -> 12246.43 | J62: =IFERROR('data sheet'!I66,0) -> 8257.24 | ... L62: =IFERROR('data sheet'!K66,0) -> 5260.06
B63: Inventory | C63: =IFERROR('data sheet'!B67,0) -> 20013.33 | D63: =IFERROR('data sheet'!C67,0) -> 24803.82 | E63: =IFERROR('data sheet'!D67,0) -> 28331.04 | F63: =IFERROR('data sheet'!E67,0) -> 31656.1 | G63: =IFERROR('data sheet'!F67,0) -> 31068.72 | H63: =IFERROR('data sheet'!G67,0) -> 33276.38 | I63: =IFERROR('data sheet'!H67,0) -> 48824.39 | J63: =IFERROR('data sheet'!I67,0) -> 54415.33 | ... L63: =IFERROR('data sheet'!K67,0) -> 44589.94
B64: Cash & Bank | C64: =IFERROR('data sheet'!B68,0) -> 6186.34 | D64: =IFERROR('data sheet'!C68,0) -> 4921.05 | E64: =IFERROR('data sheet'!D68,0) -> 7937.85 | F64: =IFERROR('data sheet'!E68,0) -> 3341.37 | G64: =IFERROR('data sheet'!F68,0) -> 8054.72 | H64: =IFERROR('data sheet'!G68,0) -> 5782.18 | I64: =IFERROR('data sheet'!H68,0) -> 15898.93 | J64: =IFERROR('data sheet'!I68,0) -> 13357.26 | ... L64: =IFERROR('data sheet'!K68,0) -> 11646.98
B65: Total Current Assests | C65: =IFERROR(SUM(C62:C64),0) -> 38265.89 | D65: =IFERROR(SUM(D62:D64),0) -> 41311.69 | E65: =IFERROR(SUM(E62:E64),0) -> 48684.41 | F65: =IFERROR(SUM(F62:F64),0) -> 46808.47 | G65: =IFERROR(SUM(G62:G64),0) -> 47008.35 | H65: =IFERROR(SUM(H62:H64),0) -> 48598.4 | I65: =IFERROR(SUM(I62:I64),0) -> 76969.75 | J65: =IFERROR(SUM(J62:J64),0) -> 76029.83 | ... L65: =IFERROR(SUM(L62:L64),0) -> 61496.98
B67: Total Assets | C67: =IFERROR(C65+C60,0) -> 176883.99 | D67: =IFERROR(D65+D60,0) -> 172447.37 | E67: =IFERROR(E65+E60,0) -> 208722.14 | F67: =IFERROR(F65+F60,0) -> 232773.44 | G67: =IFERROR(G65+G60,0) -> 249149.12 | H67: =IFERROR(H65+H60,0) -> 243909.19 | I67: =IFERROR(I65+I60,0) -> 282421.67 | J67: =IFERROR(J65+J60,0) -> 285395.78 | ... L67: =IFERROR(L65+L60,0) -> 275458.58
B69: Check | C69: =C67=C54 -> TRUE | D69: =D67=D54 -> TRUE | E69: =E67=E54 -> TRUE | F69: =F67=F54 -> TRUE | G69: =G67=G54 -> TRUE | H69: =H67=H54 -> TRUE | I69: =I67=I54 -> TRUE | J69: =J67=J54 -> TRUE | ... L69: =L67=L54 -> TRUE
A71: # | B71: Cash Flow Statements
B73: ='data sheet'!A82 -> Cash from Operating Activity | C73: ='data sheet'!B82 -> 11455.35 | D73: ='data sheet'!C82 -> 10824.36 | E73: ='data sheet'!D82 -> 8023.39 | F73: ='data sheet'!E82 -> 25335.95 | G73: ='data sheet'!F82 -> 20168.72 | H73: ='data sheet'!G82 -> 44326.68 | I73: ='data sheet'!H82 -> 44380.99 | ... L73: ='data sheet'!K82 -> 23511.81
B74: ='data sheet'!A83 -> Cash from Investing Activity | C74: ='data sheet'!B83 -> -8794.31 | D74: ='data sheet'!C83 -> -9489.65 | E74: ='data sheet'!D83 -> -11730.31 | F74: ='data sheet'!E83 -> -29176.45 | G74: ='data sheet'!F83 -> -14012.06 | H74: ='data sheet'!G83 -> -9437.27 | I74: ='data sheet'!H83 -> -10905.02 | ... L74: ='data sheet'!K83 -> -13985.25
B75: ='data sheet'!A84 -> Cash from Financing Activity | C75: ='data sheet'!B84 -> -4729.12 | D75: ='data sheet'!C84 -> -2579.36 | E75: ='data sheet'!D84 -> 6639.94 | F75: ='data sheet'!E84 -> -672.7 | G75: ='data sheet'!F84 -> -1694.62 | H75: ='data sheet'!G84 -> -37089.67 | I75: ='data sheet'!H84 -> -23401.09 | ... L75: ='data sheet'!K84 -> -7002.44
B77: ='data sheet'!A85 -> Net Cash Flow | C77: ='data sheet'!B85 -> -2068.08 | D77: ='data sheet'!C85 -> -1244.65 | E77: ='data sheet'!D85 -> 2933.02 | F77: ='data sheet'!E85 -> -4513.2 | G77: ='data sheet'!F85 -> 4462.04 | H77: ='data sheet'!G85 -> -2200.26 | I77: ='data sheet'!H85 -> 10074.88 | ... L77: ='data sheet'!K85 -> 2524.12

Sheet common size statement
B3: Common Size Income Statement- TATA STEEL LTD
B5: Particulars | D5: 42460 | E5: 42825 | F5: 43190 | G5: 43555 | H5: 43921 | I5: 44286 | J5: 44651 | K5: 45016 | L5: 45382 | M5: 45747
B7: Sales | D7: ='data sheet'!B17/'data sheet'!B$17 -> 1 | E7: ='data sheet'!C17/'data sheet'!C$17 -> 1 | F7: ='data sheet'!D17/'data sheet'!D$17 -> 1 | G7: ='data sheet'!E17/'data sheet'!E$17 -> 1 | H7: ='data sheet'!F17/'data sheet'!F$17 -> 1 | I7: ='data sheet'!G17/'data sheet'!G$17 -> 1 | J7: ='data sheet'!H17/'data sheet'!H$17 -> 1 | K7: ='data sheet'!I17/'data sheet'!I$17 -> 1 | ... M7: ='data sheet'!K17/'data sheet'!K$17 -> 1
B8: Raw Material Cost | D8: ='data sheet'!B18/'data sheet'!B$17 -> 0.37950646 | E8: ='data sheet'!C18/'data sheet'!C$17 -> 0.3904119 | F8: ='data sheet'!D18/'data sheet'!D$17 -> 0.37433962 | G8: ='data sheet'!E18/'data sheet'!E$17 -> 0.38610668 | H8: ='data sheet'!F18/'data sheet'!F$17 -> 0.41511501 | I8: ='data sheet'!G18/'data sheet'!G$17 -> 0.3521327 | J8: ='data sheet'!H18/'data sheet'!H$17 -> 0.37332727 | K8: ='data sheet'!I18/'data sheet'!I$17 -> 0.47912842 | ... M8: ='data sheet'!K18/'data sheet'!K$17 -> 0.43514326
B9: Change in Inventory | D9: ='data sheet'!B19/'data sheet'!B$17 -> -0.018880942 | E9: ='data sheet'!C19/'data sheet'!C$17 -> 0.040410983 | F9: ='data sheet'!D19/'data sheet'!D$17 -> -0.00080576673 | G9: ='data sheet'!E19/'data sheet'!E$17 -> 0.00061337363 | H9: ='data sheet'!F19/'data sheet'!F$17 -> 0.0040427231 | I9: ='data sheet'!G19/'data sheet'!G$17 -> -0.0096932209 | J9: ='data sheet'!H19/'data sheet'!H$17 -> 0.031144023 | K9: ='data sheet'!I19/'data sheet'!I$17 -> 0.01380256 | ... M9: ='data sheet'!K19/'data sheet'!K$17 -> 0.00044224806
B10: Power and Fuel | D10: ='data sheet'!B20/'data sheet'!B$17 -> 0.048976646 | E10: ='data sheet'!C20/'data sheet'!C$17 -> 0.046490267 | F10: ='data sheet'!D20/'data sheet'!D$17 -> 0.036028101 | G10: ='data sheet'!E20/'data sheet'!E$17 -> 0.033719757 | H10: ='data sheet'!F20/'data sheet'!F$17 -> 0.03804926 | I10: ='data sheet'!G20/'data sheet'!G$17 -> 0.036480795 | J10: ='data sheet'!H20/'data sheet'!H$17 -> 0.032908335 | K10: ='data sheet'!I20/'data sheet'!I$17 -> 0.039148571 | ... M10: ='data sheet'!K20/'data sheet'!K$17 -> 0.060056279
B11: Other Mfr. Exp | D11: ='data sheet'!B21/'data sheet'!B$17 -> 0.15725321 | E11: ='data sheet'!C21/'data sheet'!C$17 -> 0.14068764 | F11: ='data sheet'!D21/'data sheet'!D$17 -> 0.13757337 | G11: ='data sheet'!E21/'data sheet'!E$17 -> 0.13150512 | H11: ='data sheet'!F21/'data sheet'!F$17 -> 0.15186096 | I11: ='data sheet'!G21/'data sheet'!G$17 -> 0.13257461 | J11: ='data sheet'!H21/'data sheet'!H$17 -> 0.11819215 | K11: ='data sheet'!I21/'data sheet'!I$17 -> 0.1362008 | ... M11: ='data sheet'!K21/'data sheet'!K$17 -> 0.17708454
B12: Employee Cost | D12: ='data sheet'!B22/'data sheet'!B$17 -> 0.17248741 | E12: ='data sheet'!C22/'data sheet'!C$17 -> 0.15362697 | F12: ='data sheet'!D22/'data sheet'!D$17 -> 0.13856096 | G12: ='data sheet'!E22/'data sheet'!E$17 -> 0.11897628 | H12: ='data sheet'!F22/'data sheet'!F$17 -> 0.13255632 | I12: ='data sheet'!G22/'data sheet'!G$17 -> 0.12723122 | J12: ='data sheet'!H22/'data sheet'!H$17 -> 0.095360629 | K12: ='data sheet'!I22/'data sheet'!I$17 -> 0.092126863 | ... M12: ='data sheet'!K22/'data sheet'!K$17 -> 0.11388626
B13: Selling and admin | D13: ='data sheet'!B23/'data sheet'!B$17 -> 0.12659692 | E13: ='data sheet'!C23/'data sheet'!C$17 -> 0.12263928 | F13: ='data sheet'!D23/'data sheet'!D$17 -> 0.11703025 | G13: ='data sheet'!E23/'data sheet'!E$17 -> 0.10729529 | H13: ='data sheet'!F23/'data sheet'!F$17 -> 0.11156804 | I13: ='data sheet'!G23/'data sheet'!G$17 -> 0.11189967 | J13: ='data sheet'!H23/'data sheet'!H$17 -> 0.11250108 | K13: ='data sheet'!I23/'data sheet'!I$17 -> 0.10486804 | ... M13: ='data sheet'!K23/'data sheet'!K$17 -> 0.055537296
B14: Other Expenses | D14: ='data sheet'!B24/'data sheet'!B$17 -> 0.10243033 | E14: ='data sheet'!C24/'data sheet'!C$17 -> 0.069513983 | F14: ='data sheet'!D24/'data sheet'!D$17 -> 0.021760489 | G14: ='data sheet'!E24/'data sheet'!E$17 -> 0.037062329 | H14: ='data sheet'!F24/'data sheet'!F$17 -> 0.029993424 | I14: ='data sheet'!G24/'data sheet'!G$17 -> 0.03504423 | J14: ='data sheet'!H24/'data sheet'!H$17 -> 0.038606296 | K14: ='data sheet'!I24/'data sheet'!I$17 -> 0.029600043 | ... M14: ='data sheet'!K24/'data sheet'!K$17 -> 0.042974751
B15: Other Income | D15: ='data sheet'!B25/'data sheet'!B$17 -> 0.10146519 | E15: ='data sheet'!C25/'data sheet'!C$17 -> -0.033741136 | F15: ='data sheet'!D25/'data sheet'!D$17 -> 0.0884259 | G15: ='data sheet'!E25/'data sheet'!E$17 -> 0.0096677857 | H15: ='data sheet'!F25/'data sheet'!F$17 -> -0.020624368 | I15: ='data sheet'!G25/'data sheet'!G$17 -> 0.0011489199 | J15: ='data sheet'!H25/'data sheet'!H$17 -> 0.0053287196 | K15: ='data sheet'!I25/'data sheet'!I$17 -> 0.006446857 | ... M15: ='data sheet'!K25/'data sheet'!K$17 -> 0.0040115765
B16: Depreciation | D16: ='data sheet'!B26/'data sheet'!B$17 -> 0.052041039 | E16: ='data sheet'!C26/'data sheet'!C$17 -> 0.050515666 | F16: ='data sheet'!D26/'data sheet'!D$17 -> 0.046586153 | G16: ='data sheet'!E26/'data sheet'!E$17 -> 0.046564832 | H16: ='data sheet'!F26/'data sheet'!F$17 -> 0.060369992 | I16: ='data sheet'!G26/'data sheet'!G$17 -> 0.059009416 | J16: ='data sheet'!H26/'data sheet'!H$17 -> 0.03730489 | K16: ='data sheet'!I26/'data sheet'!I$17 -> 0.038360784 | ... M16: ='data sheet'!K26/'data sheet'!K$17 -> 0.047685597
B17: Interest | D17: ='data sheet'!B27/'data sheet'!B$17 -> 0.041400692 | E17: ='data sheet'!C27/'data sheet'!C$17 -> 0.045166752 | F17: ='data sheet'!D27/'data sheet'!D$17 -> 0.044257859 | G17: ='data sheet'!E27/'data sheet'!E$17 -> 0.048583428 | H17: ='data sheet'!F27/'data sheet'!F$17 -> 0.053880993 | I17: ='data sheet'!G27/'data sheet'!G$17 -> 0.048612196 | J17: ='data sheet'!H27/'data sheet'!H$17 -> 0.022389812 | K17: ='data sheet'!I27/'data sheet'!I$17 -> 0.02588301 | ... M17: ='data sheet'!K27/'data sheet'!K$17 -> 0.03359049
B18: Profit before tax | D18: ='data sheet'!B28/'data sheet'!B$17 -> 0.0018915366 | E18: ='data sheet'!C28/'data sheet'!C$17 -> -0.012382611 | F18: ='data sheet'!D28/'data sheet'!D$17 -> 0.17148332 | G18: ='data sheet'!E28/'data sheet'!E$17 -> 0.10046744 | H18: ='data sheet'!F28/'data sheet'!F$17 -> -0.0099756359 | I18: ='data sheet'!G28/'data sheet'!G$17 -> 0.088470859 | J18: ='data sheet'!H28/'data sheet'!H$17 -> 0.20588228 | K18: ='data sheet'!I28/'data sheet'!I$17 -> 0.074932889 | ... M18: ='data sheet'!K28/'data sheet'!K$17 -> 0.038495348
... B22: EBITDA | D22: ='data sheet'!B32/'data sheet'!B$17 -> 0.096454342 | E22: ='data sheet'!C32/'data sheet'!C$17 -> 0.082656616 | F22: ='data sheet'!D32/'data sheet'!D$17 -> 0.22736967 | G22: ='data sheet'!E32/'data sheet'!E$17 -> 0.20256799 | H22: ='data sheet'!F32/'data sheet'!F$17 -> 0.10701386 | I22: ='data sheet'!G32/'data sheet'!G$17 -> 0.19162173 | J22: ='data sheet'!H32/'data sheet'!H$17 -> 0.2590374 | K22: ='data sheet'!I32/'data sheet'!I$17 -> 0.14199173 | ... M22: ='data sheet'!K32/'data sheet'!K$17 -> 0.12090041
B24: Common Size Balance Sheet- TATA STEEL LTD
B26: Particulars | D26: 42460 | E26: 42825 | F26: 43190 | G26: 43555 | H26: 43921 | I26: 44286 | J26: 44651 | K26: 45016 | L26: 45382 | M26: 45747
B28: Total Liabilities | D28: ='data sheet'!B60/'data sheet'!B$60 -> 1 | E28: ='data sheet'!C60/'data sheet'!C$60 -> 1 | F28: ='data sheet'!D60/'data sheet'!D$60 -> 1 | G28: ='data sheet'!E60/'data sheet'!E$60 -> 1 | H28: ='data sheet'!F60/'data sheet'!F$60 -> 1 | I28: ='data sheet'!G60/'data sheet'!G$60 -> 1 | J28: ='data sheet'!H60/'data sheet'!H$60 -> 1 | K28: ='data sheet'!I60/'data sheet'!I$60 -> 1 | ... M28: ='data sheet'!K60/'data sheet'!K$60 -> 1
B29: Equity Share Capital | D29: ='data sheet'!B56/'data sheet'!B$60 -> 0.005485177 | E29: ='data sheet'!C56/'data sheet'!C$60 -> 0.0056262963 | F29: ='data sheet'!D56/'data sheet'!D$60 -> 0.0054855225 | G29: ='data sheet'!E56/'data sheet'!E$60 -> 0.0049186883 | H29: ='data sheet'!F56/'data sheet'!F$60 -> 0.0045954407 | I29: ='data sheet'!G56/'data sheet'!G$60 -> 0.0049100651 | J29: ='data sheet'!H56/'data sheet'!H$60 -> 0.0043240662 | K29: ='data sheet'!I56/'data sheet'!I$60 -> 0.0042791102 | ... M29: ='data sheet'!K56/'data sheet'!K$60 -> 0.0045285937
B30: Reserves | D30: ='data sheet'!B57/'data sheet'!B$60 -> 0.24175342 | E30: ='data sheet'!C57/'data sheet'!C$60 -> 0.21368305 | F30: ='data sheet'!D57/'data sheet'!D$60 -> 0.28614918 | G30: ='data sheet'!E57/'data sheet'!E$60 -> 0.29118503 | H30: ='data sheet'!F57/'data sheet'!F$60 -> 0.29071485 | I30: ='data sheet'!G57/'data sheet'!G$60 -> 0.29946047 | J30: ='data sheet'!H57/'data sheet'!H$60 -> 0.4008964 | K30: ='data sheet'!I57/'data sheet'!I$60 -> 0.35691088 | ... M30: ='data sheet'!K57/'data sheet'!K$60 -> 0.32644541
B31: Borrowings | D31: ='data sheet'!B58/'data sheet'!B$60 -> 0.46350679 | E31: ='data sheet'!C58/'data sheet'!C$60 -> 0.48139029 | F31: ='data sheet'!D58/'data sheet'!D$60 -> 0.44148191 | G31: ='data sheet'!E58/'data sheet'!E$60 -> 0.43310878 | H31: ='data sheet'!F58/'data sheet'!F$60 -> 0.46690191 | I31: ='data sheet'!G58/'data sheet'!G$60 -> 0.36284574 | J31: ='data sheet'!H58/'data sheet'!H$60 -> 0.26754799 | K31: ='data sheet'!I58/'data sheet'!I$60 -> 0.29745727 | ... M31: ='data sheet'!K58/'data sheet'!K$60 -> 0.34415719
B32: Other Liabilities | D32: ='data sheet'!B59/'data sheet'!B$60 -> 0.28925461 | E32: ='data sheet'!C59/'data sheet'!C$60 -> 0.29930036 | F32: ='data sheet'!D59/'data sheet'!D$60 -> 0.26688338 | G32: ='data sheet'!E59/'data sheet'!E$60 -> 0.27078751 | H32: ='data sheet'!F59/'data sheet'!F$60 -> 0.2377878 | I32: ='data sheet'!G59/'data sheet'!G$60 -> 0.33278373 | J32: ='data sheet'!H59/'data sheet'!H$60 -> 0.32723155 | K32: ='data sheet'!I59/'data sheet'!I$60 -> 0.34135273 | ... M32: ='data sheet'!K59/'data sheet'!K$60 -> 0.32486881
B34: Total Assets | D34: ='data sheet'!B65/'data sheet'!B$65 -> 1 | E34: ='data sheet'!C65/'data sheet'!C$65 -> 1 | F34: ='data sheet'!D65/'data sheet'!D$65 -> 1 | G34: ='data sheet'!E65/'data sheet'!E$65 -> 1 | H34: ='data sheet'!F65/'data sheet'!F$65 -> 1 | I34: ='data sheet'!G65/'data sheet'!G$65 -> 1 | J34: ='data sheet'!H65/'data sheet'!H$65 -> 1 | K34: ='data sheet'!I65/'data sheet'!I$65 -> 1 | ... M34: ='data sheet'!K65/'data sheet'!K$65 -> 1
B35: Net Block | D35: ='data sheet'!B61/'data sheet'!B$65 -> 0.40817578 | E35: ='data sheet'!C61/'data sheet'!C$65 -> 0.53353409 | F35: ='data sheet'!D61/'data sheet'!D$65 -> 0.46044416 | G35: ='data sheet'!E61/'data sheet'!E$65 -> 0.53460528 | H35: ='data sheet'!F61/'data sheet'!F$65 -> 0.54004068 | I35: ='data sheet'!G61/'data sheet'!G$65 -> 0.55666283 | J35: ='data sheet'!H61/'data sheet'!H$65 -> 0.47194619 | K35: ='data sheet'!I61/'data sheet'!I$65 -> 0.51374782 | ... M35: ='data sheet'!K61/'data sheet'!K$65 -> 0.5478648
B36: Capital Work in Progress | D36: ='data sheet'!B62/'data sheet'!B$65 -> 0.20350112 | E36: ='data sheet'!C62/'data sheet'!C$65 -> 0.091530129 | F36: ='data sheet'!D62/'data sheet'!D$65 -> 0.079600612 | G36: ='data sheet'!E62/'data sheet'!E$65 -> 0.080083063 | H36: ='data sheet'!F62/'data sheet'!F$65 -> 0.078253658 | I36: ='data sheet'!G62/'data sheet'!G$65 -> 0.077928183 | J36: ='data sheet'!H62/'data sheet'!H$65 -> 0.078058989 | K36: ='data sheet'!I62/'data sheet'!I$65 -> 0.10936749 | ... M36: ='data sheet'!K62/'data sheet'!K$65 -> 0.15110203
B37: Investments | D37: ='data sheet'!B63/'data sheet'!B$65 -> 0.060569133 | E37: ='data sheet'!C63/'data sheet'!C$65 -> 0.072237228 | F37: ='data sheet'!D63/'data sheet'!D$65 -> 0.085757409 | G37: ='data sheet'!E63/'data sheet'!E$65 -> 0.024651309 | H37: ='data sheet'!F63/'data sheet'!F$65 -> 0.025226579 | I37: ='data sheet'!G63/'data sheet'!G$65 -> 0.043794701 | J37: ='data sheet'!H63/'data sheet'!H$65 -> 0.046525644 | K37: ='data sheet'!I63/'data sheet'!I$65 -> 0.029468936 | ... M37: ='data sheet'!K63/'data sheet'!K$65 -> 0.022486539
B38: Other Assets | D38: ='data sheet'!B73/'data sheet'!B$74 -> 0.11142071 | E38: ='data sheet'!C73/'data sheet'!C$74 -> 0.063137408 | F38: ='data sheet'!D73/'data sheet'!D$74 -> 0.14094796 | G38: ='data sheet'!E73/'data sheet'!E$74 -> 0.1595701 | H38: ='data sheet'!F73/'data sheet'!F$74 -> 0.16780352 | I38: ='data sheet'!G73/'data sheet'!G$74 -> 0.12236636 | J38: ='data sheet'!H73/'data sheet'!H$74 -> 0.13093432 | K38: ='data sheet'!I73/'data sheet'!I$74 -> 0.081014372 | ... M38: ='data sheet'!K73/'data sheet'!K$74 -> 0.05529354
B39: Receivables | D39: ='data sheet'!B66/'data sheet'!B$74 -> 0.068215444 | E39: ='data sheet'!C66/'data sheet'!C$74 -> 0.067190471 | F39: ='data sheet'!D66/'data sheet'!D$74 -> 0.059483484 | G39: ='data sheet'!E66/'data sheet'!E$74 -> 0.050740325 | H39: ='data sheet'!F66/'data sheet'!F$74 -> 0.031647352 | I39: ='data sheet'!G66/'data sheet'!G$74 -> 0.039112261 | J39: ='data sheet'!H66/'data sheet'!H$74 -> 0.043362218 | K39: ='data sheet'!I66/'data sheet'!I$74 -> 0.028932593 | ... M39: ='data sheet'!K66/'data sheet'!K$74 -> 0.019095648
B40: Inventory | D40: ='data sheet'!B67/'data sheet'!B$74 -> 0.11314382 | E40: ='data sheet'!C67/'data sheet'!C$74 -> 0.14383414 | F40: ='data sheet'!D67/'data sheet'!D$74 -> 0.13573567 | G40: ='data sheet'!E67/'data sheet'!E$74 -> 0.13599533 | H40: ='data sheet'!F67/'data sheet'!F$74 -> 0.1246993 | I40: ='data sheet'!G67/'data sheet'!G$74 -> 0.13642938 | J40: ='data sheet'!H67/'data sheet'!H$74 -> 0.17287763 | K40: ='data sheet'!I67/'data sheet'!I$74 -> 0.1906662 | ... M40: ='data sheet'!K67/'data sheet'!K$74 -> 0.1618753
B41: Cash & Bank | D41: ='data sheet'!B68/'data sheet'!B$74 -> 0.034973996 | E41: ='data sheet'!C68/'data sheet'!C$74 -> 0.028536533 | F41: ='data sheet'!D68/'data sheet'!D$74 -> 0.038030704 | G41: ='data sheet'!E68/'data sheet'!E$74 -> 0.014354602 | H41: ='data sheet'!F68/'data sheet'!F$74 -> 0.032328912 | I41: ='data sheet'!G68/'data sheet'!G$74 -> 0.023706282 | J41: ='data sheet'!H68/'data sheet'!H$74 -> 0.056295007 | K41: ='data sheet'!I68/'data sheet'!I$74 -> 0.046802584 | ... M41: ='data sheet'!K68/'data sheet'!K$74 -> 0.042282146

Sheet Ratio Analysis
B2: Ratio Analysis of - TATA STEEL LTD
B3: Years | C3: 42460 | D3: 42825 | E3: 43190 | F3: 43555 | G3: 43921 | H3: 44286 | I3: 44651 | J3: 45016 | K3: 45382 | L3: 45747 | M3: Trend | N3: Mean | O3: Median
B5: Sales Growth | C5: =IFERROR('HISTORICAL(FS)'!C8,0) -> - | D5: =IFERROR('HISTORICAL(FS)'!D8,0) -> 0.10135565 | E5: =IFERROR('HISTORICAL(FS)'!E8,0) -> 0.097504065 | F5: =IFERROR('HISTORICAL(FS)'!F8,0) -> 0.27927124 | G5: =IFERROR('HISTORICAL(FS)'!G8,0) -> -0.1132267 | H5: =IFERROR('HISTORICAL(FS)'!H8,0) -> 0.11916142 | I5: =IFERROR('HISTORICAL(FS)'!I8,0) -> 0.55906968 | J5: =IFERROR('HISTORICAL(FS)'!J8,0) -> -0.0024859898 | ... L5: =IFERROR('HISTORICAL(FS)'!L8,0) -> -0.046377073 | N5: =IFERROR(AVERAGE(D5:L5),0) -> 0.10399945 | O5: =IFERROR(MEDIAN(C5:L5),0) -> 0.097504065
B6: EBITDA Growth | C6: - | D6: =IFERROR('HISTORICAL(FS)'!D19/'HISTORICAL(FS)'!C19-1,0) -> -22.021736 | E6: =IFERROR('HISTORICAL(FS)'!E19/'HISTORICAL(FS)'!D19-1,0) -> 0.6306903 | F6: =IFERROR('HISTORICAL(FS)'!F19/'HISTORICAL(FS)'!E19-1,0) -> 0.36788877 | G6: =IFERROR('HISTORICAL(FS)'!G19/'HISTORICAL(FS)'!F19-1,0) -> -0.40436152 | H6: =IFERROR('HISTORICAL(FS)'!H19/'HISTORICAL(FS)'!G19-1,0) -> 0.74678779 | I6: =IFERROR('HISTORICAL(FS)'!I19/'HISTORICAL(FS)'!H19-1,0) -> 1.081347 | J6: =IFERROR('HISTORICAL(FS)'!J19/'HISTORICAL(FS)'!I19-1,0) -> -0.49125555 | K6: =IFERROR('HISTORICAL(FS)'!K19/'HISTORICAL(FS)'!J19-1,0) -> -0.31121332 | L6: =IFERROR('HISTORICAL(FS)'!L19/'HISTORICAL(FS)'!K19-1,0) -> 0.13711529 | N6: =IFERROR(AVERAGE(D6:L6),0) -> -2.2516374 | O6: =IFERROR(MEDIAN(C6:L6),0) -> 0.13711529
B7: EBIT Growth | C7: - | D7: =IFERROR('HISTORICAL(FS)'!D28/'HISTORICAL(FS)'!C28-1,0) -> -1.2362405 | E7: =IFERROR('HISTORICAL(FS)'!E28/'HISTORICAL(FS)'!D28-1,0) -> 3.267891 | F7: =IFERROR('HISTORICAL(FS)'!F28/'HISTORICAL(FS)'!E28-1,0) -> 0.39851906 | G7: =IFERROR('HISTORICAL(FS)'!G28/'HISTORICAL(FS)'!F28-1,0) -> -0.89600169 | H7: =IFERROR('HISTORICAL(FS)'!H28/'HISTORICAL(FS)'!G28-1,0) -> 8.1773694 | I7: =IFERROR('HISTORICAL(FS)'!I28/'HISTORICAL(FS)'!H28-1,0) -> 2.5807379 | J7: =IFERROR('HISTORICAL(FS)'!J28/'HISTORICAL(FS)'!I28-1,0) -> -0.65936393 | K7: =IFERROR('HISTORICAL(FS)'!K28/'HISTORICAL(FS)'!J28-1,0) -> -0.70850149 | L7: =IFERROR('HISTORICAL(FS)'!L28/'HISTORICAL(FS)'!K28-1,0) -> 0.55122998 | N7: =IFERROR(AVERAGE(D7:L7),0) -> 1.2750711 | O7: =IFERROR(MEDIAN(C7:L7),0) -> 0.39851906
B8: Net Profit Growth | C8: - | D8: =IFERROR('HISTORICAL(FS)'!D34/'HISTORICAL(FS)'!C34-1,0) -> -0.96500402 | E8: =IFERROR('HISTORICAL(FS)'!E34/'HISTORICAL(FS)'!D34-1,0) -> -19.037263 | F8: =IFERROR('HISTORICAL(FS)'!F34/'HISTORICAL(FS)'!E34-1,0) -> 0.11008091 | G8: =IFERROR('HISTORICAL(FS)'!G34/'HISTORICAL(FS)'!F34-1,0) -> -0.465997 | H8: =IFERROR('HISTORICAL(FS)'!H34/'HISTORICAL(FS)'!G34-1,0) -> 0.9742315 | I8: =IFERROR('HISTORICAL(FS)'!I34/'HISTORICAL(FS)'!H34-1,0) -> 4.0498476 | J8: =IFERROR('HISTORICAL(FS)'!J34/'HISTORICAL(FS)'!I34-1,0) -> -0.83914468 | K8: =IFERROR('HISTORICAL(FS)'!K34/'HISTORICAL(FS)'!J34-1,0) -> -0.83161121 | L8: =IFERROR('HISTORICAL(FS)'!L34/'HISTORICAL(FS)'!K34-1,0) -> 1.0966028 | N8: =IFERROR(AVERAGE(D8:L8),0) -> -1.7675842 | O8: =IFERROR(MEDIAN(C8:L8),0) -> -0.465997
B9: Divident Growth | C9: - | D9: =IFERROR('HISTORICAL(FS)'!D42/'HISTORICAL(FS)'!C42-1,0) -> 0.25000322 | E9: =IFERROR('HISTORICAL(FS)'!E42/'HISTORICAL(FS)'!D42-1,0) -> 0.18021551 | F9: =IFERROR('HISTORICAL(FS)'!F42/'HISTORICAL(FS)'!E42-1,0) -> 0.29997536 | G9: =IFERROR('HISTORICAL(FS)'!G42/'HISTORICAL(FS)'!F42-1,0) -> -0.23076148 | H9: =IFERROR('HISTORICAL(FS)'!H42/'HISTORICAL(FS)'!G42-1,0) -> 1.4617851 | I9: =IFERROR('HISTORICAL(FS)'!I42/'HISTORICAL(FS)'!H42-1,0) -> 1.0381154 | J9: =IFERROR('HISTORICAL(FS)'!J42/'HISTORICAL(FS)'!I42-1,0) -> -0.29459179 | K9: =IFERROR('HISTORICAL(FS)'!K42/'HISTORICAL(FS)'!J42-1,0) -> 1.5657977e-05 | L9: =IFERROR('HISTORICAL(FS)'!L42/'HISTORICAL(FS)'!K42-1,0) -> 0 | N9: =IFERROR(AVERAGE(D9:L9),0) -> 0.30052856 | O9: =IFERROR(MEDIAN(C9:L9),0) -> 0.18021551
B11: Gross Margin | C11: =IFERROR('HISTORICAL(FS)'!C14,0) -> 0.22289533 | D11: =IFERROR('HISTORICAL(FS)'!D14,0) -> 0.30919421 | E11: =IFERROR('HISTORICAL(FS)'!E14,0) -> 0.31269218 | F11: =IFERROR('HISTORICAL(FS)'!F14,0) -> 0.33030553 | G11: =IFERROR('HISTORICAL(FS)'!G14,0) -> 0.26646118 | H11: =IFERROR('HISTORICAL(FS)'!H14,0) -> 0.34188745 | I11: =IFERROR('HISTORICAL(FS)'!I14,0) -> 0.41135564 | J11: =IFERROR('HISTORICAL(FS)'!J14,0) -> 0.26719791 | ... L11: =IFERROR('HISTORICAL(FS)'!L14,0) -> 0.21427191 | N11: =IFERROR(AVERAGE(C11:L11),0) -> 0.28770546 | O11: =IFERROR('HISTORICAL(FS)'!O14,0) -> 0
B12: EBITDA Margin | C12: =IFERROR('HISTORICAL(FS)'!C20,0) -> -0.0061319248 | D12: =IFERROR('HISTORICAL(FS)'!D20,0) -> 0.11704094 | E12: =IFERROR('HISTORICAL(FS)'!E20,0) -> 0.17390143 | F12: =IFERROR('HISTORICAL(FS)'!F20,0) -> 0.18594792 | G12: =IFERROR('HISTORICAL(FS)'!G20,0) -> 0.12489972 | H12: =IFERROR('HISTORICAL(FS)'!H20,0) -> 0.19494355 | I12: =IFERROR('HISTORICAL(FS)'!I20,0) -> 0.26024826 | J12: =IFERROR('HISTORICAL(FS)'!J20,0) -> 0.13272983 | ... L12: =IFERROR('HISTORICAL(FS)'!L20,0) -> 0.11575986 | N12: =IFERROR(AVERAGE(C12:L12),0) -> 0.13964197 | O12: =IFERROR('HISTORICAL(FS)'!O20,0) -> 0
B13: EBIT Margin | C13: =IFERROR(('HISTORICAL(FS)'!C19-'HISTORICAL(FS)'!C25)/'HISTORICAL(FS)'!C7,0) -> -0.058172964 | D13: =IFERROR(('HISTORICAL(FS)'!D19-'HISTORICAL(FS)'!D25)/'HISTORICAL(FS)'!D7,0) -> 0.066525277 | E13: =IFERROR(('HISTORICAL(FS)'!E19-'HISTORICAL(FS)'!E25)/'HISTORICAL(FS)'!E7,0) -> 0.12731528 | F13: =IFERROR(('HISTORICAL(FS)'!F19-'HISTORICAL(FS)'!F25)/'HISTORICAL(FS)'!F7,0) -> 0.13938308 | G13: =IFERROR(('HISTORICAL(FS)'!G19-'HISTORICAL(FS)'!G25)/'HISTORICAL(FS)'!G7,0) -> 0.064529725 | H13: =IFERROR(('HISTORICAL(FS)'!H19-'HISTORICAL(FS)'!H25)/'HISTORICAL(FS)'!H7,0) -> 0.13593413 | I13: =IFERROR(('HISTORICAL(FS)'!I19-'HISTORICAL(FS)'!I25)/'HISTORICAL(FS)'!I7,0) -> 0.22294337 | J13: =IFERROR(('HISTORICAL(FS)'!J19-'HISTORICAL(FS)'!J25)/'HISTORICAL(FS)'!J7,0) -> 0.094369041 | ... L13: =IFERROR(('HISTORICAL(FS)'!L19-'HISTORICAL(FS)'!L25)/'HISTORICAL(FS)'!L7,0) -> 0.068074262 | N13: =IFERROR(AVERAGE(C13:L13),0) -> 0.091485992 | O13: =IFERROR(('HISTORICAL(FS)'!O19-'HISTORICAL(FS)'!O25)/'HISTORICAL(FS)'!O7,0) -> 0
B14: EBT Margin | C14: =IFERROR('HISTORICAL(FS)'!C29,0) -> -0.099573656 | D14: =IFERROR('HISTORICAL(FS)'!D29,0) -> 0.021358525 | E14: =IFERROR('HISTORICAL(FS)'!E29,0) -> 0.083057422 | F14: =IFERROR('HISTORICAL(FS)'!F29,0) -> 0.090799656 | G14: =IFERROR('HISTORICAL(FS)'!G29,0) -> 0.010648732 | H14: =IFERROR('HISTORICAL(FS)'!H29,0) -> 0.087321939 | I14: =IFERROR('HISTORICAL(FS)'!I29,0) -> 0.20055356 | J14: =IFERROR('HISTORICAL(FS)'!J29,0) -> 0.068486032 | ... L14: =IFERROR('HISTORICAL(FS)'!L29,0) -> 0.034483772 | N14: =IFERROR(AVERAGE(C14:L14),0) -> 0.051833497 | O14: =IFERROR('HISTORICAL(FS)'!O29,0) -> 0
B15: Net Profit Margin | C15: =IFERROR('HISTORICAL(FS)'!C35,0) -> -0.10634031 | D15: =IFERROR('HISTORICAL(FS)'!D35,0) -> -0.0033790023 | E15: =IFERROR('HISTORICAL(FS)'!E35,0) -> 0.055533239 | F15: =IFERROR('HISTORICAL(FS)'!F35,0) -> 0.048188677 | G15: =IFERROR('HISTORICAL(FS)'!G35,0) -> 0.029018575 | H15: =IFERROR('HISTORICAL(FS)'!H35,0) -> 0.051189565 | I15: =IFERROR('HISTORICAL(FS)'!I35,0) -> 0.16580369 | J15: =IFERROR('HISTORICAL(FS)'!J35,0) -> 0.026736873 | ... L15: =IFERROR('HISTORICAL(FS)'!L35,0) -> 0.010510907 | N15: =IFERROR(AVERAGE(C15:L15),0) -> 0.028204301 | O15: =IFERROR(MEDIAN(C15:L15),0) -> 0.027877724
B17: Sales Expenses % Sales | C17: =IFERROR('HISTORICAL(FS)'!C17,0) -> 0.22902726 | D17: =IFERROR('HISTORICAL(FS)'!D17,0) -> 0.19215326 | E17: =IFERROR('HISTORICAL(FS)'!E17,0) -> 0.13879074 | F17: =IFERROR('HISTORICAL(FS)'!F17,0) -> 0.14435762 | G17: =IFERROR('HISTORICAL(FS)'!G17,0) -> 0.14156147 | H17: =IFERROR('HISTORICAL(FS)'!H17,0) -> 0.1469439 | I17: =IFERROR('HISTORICAL(FS)'!I17,0) -> 0.15110738 | J17: =IFERROR('HISTORICAL(FS)'!J17,0) -> 0.13446808 | ... L17: =IFERROR('HISTORICAL(FS)'!L17,0) -> 0.098512047 | N17: =IFERROR(AVERAGE(C17:L17),0) -> 0.14806349 | O17: =IFERROR(MEDIAN(C17:L17),0) -> 0.14295954
B18: Depreciation % Sales | C18: =IFERROR('HISTORICAL(FS)'!C26,0) -> 0.052041039 | D18: =IFERROR('HISTORICAL(FS)'!D26,0) -> 0.050515666 | E18: =IFERROR('HISTORICAL(FS)'!E26,0) -> 0.046586153 | F18: =IFERROR('HISTORICAL(FS)'!F26,0) -> 0.046564832 | G18: =IFERROR('HISTORICAL(FS)'!G26,0) -> 0.060369992 | H18: =IFERROR('HISTORICAL(FS)'!H26,0) -> 0.059009416 | I18: =IFERROR('HISTORICAL(FS)'!I26,0) -> 0.03730489 | J18: =IFERROR('HISTORICAL(FS)'!J26,0) -> 0.038360784 | ... L18: =IFERROR('HISTORICAL(FS)'!L26,0) -> 0.047685597 | N18: =IFERROR(AVERAGE(C18:L18),0) -> 0.048155975 | O18: =IFERROR(MEDIAN(C18:L18),0) -> 0.047135875
B19: Operating income % Sales | C19: =IFERROR(C13,0) -> -0.058172964 | D19: =IFERROR(D13,0) -> 0.066525277 | E19: =IFERROR(E13,0) -> 0.12731528 | F19: =IFERROR(F13,0) -> 0.13938308 | G19: =IFERROR(G13,0) -> 0.064529725 | H19: =IFERROR(H13,0) -> 0.13593413 | I19: =IFERROR(I13,0) -> 0.22294337 | J19: =IFERROR(J13,0) -> 0.094369041 | ... L19: =IFERROR(L13,0) -> 0.068074262 | N19: =IFERROR(AVERAGE(C19:L19),0) -> 0.091485992 | O19: =IFERROR(MEDIAN(C19:L19),0) -> 0.081221651
B21: Return on Capital Employed | C21: =IFERROR(('HISTORICAL(FS)'!C19-'HISTORICAL(FS)'!C25)/(SUM('HISTORICAL(FS)'!C50:C52)),0) -> -0.047181153 | D21: =IFERROR(('HISTORICAL(FS)'!D19-'HISTORICAL(FS)'!D25)/(SUM('HISTORICAL(FS)'!D50:D52)),0) -> 0.061826653 | E21: =IFERROR(('HISTORICAL(FS)'!E19-'HISTORICAL(FS)'!E25)/(SUM('HISTORICAL(FS)'!E50:E52)),0) -> 0.10254692 | F21: =IFERROR(('HISTORICAL(FS)'!F19-'HISTORICAL(FS)'!F25)/(SUM('HISTORICAL(FS)'!F50:F52)),0) -> 0.12946991 | G21: =IFERROR(('HISTORICAL(FS)'!G19-'HISTORICAL(FS)'!G25)/(SUM('HISTORICAL(FS)'!G50:G52)),0) -> 0.047509827 | H21: =IFERROR(('HISTORICAL(FS)'!H19-'HISTORICAL(FS)'!H25)/(SUM('HISTORICAL(FS)'!H50:H52)),0) -> 0.13070294 | I21: =IFERROR(('HISTORICAL(FS)'!I19-'HISTORICAL(FS)'!I25)/(SUM('HISTORICAL(FS)'!I50:I52)),0) -> 0.2862517 | J21: =IFERROR(('HISTORICAL(FS)'!J19-'HISTORICAL(FS)'!J25)/(SUM('HISTORICAL(FS)'!J50:J52)),0) -> 0.12217019 | ... L21: =IFERROR(('HISTORICAL(FS)'!L19-'HISTORICAL(FS)'!L25)/(SUM('HISTORICAL(FS)'!L50:L52)),0) -> 0.079997126 | N21: =IFERROR(AVERAGE(C21:L21),0) -> 0.09823311 | O21: =IFERROR(MEDIAN(C21:L21),0) -> 0.091272021
B22: Retained Earnings % | C22: =IFERROR('HISTORICAL(FS)'!C45,0) -> 0 | D22: =IFERROR('HISTORICAL(FS)'!D45,0) -> 0 | E22: =IFERROR('HISTORICAL(FS)'!E45,0) -> 0.83271775 | F22: =IFERROR('HISTORICAL(FS)'!F45,0) -> 0.8041001 | G22: =IFERROR('HISTORICAL(FS)'!G45,0) -> 0.71780355 | H22: =IFERROR('HISTORICAL(FS)'!H45,0) -> 0.6262152 | I22: =IFERROR('HISTORICAL(FS)'!I45,0) -> 0.84602539 | J22: =IFERROR('HISTORICAL(FS)'!J45,0) -> 0.3242962 | ... L22: =IFERROR('HISTORICAL(FS)'!L45,0) -> 0 | N22: =IFERROR(AVERAGE(C22:L22),0) -> 0.41511582 | O22: =IFERROR(MEDIAN(C22:L22),0) -> 0.4752557
B23: Return on Equity % | C23: =IFERROR('HISTORICAL(FS)'!C34/SUM('HISTORICAL(FS)'!C50:C51),0) -> -0.24793798 | D23: =IFERROR('HISTORICAL(FS)'!D34/SUM('HISTORICAL(FS)'!D50:D51),0) -> -0.010033496 | E23: =IFERROR('HISTORICAL(FS)'!E34/SUM('HISTORICAL(FS)'!E50:E51),0) -> 0.11244209 | F23: =IFERROR('HISTORICAL(FS)'!F34/SUM('HISTORICAL(FS)'!F50:F51),0) -> 0.1102336 | G23: =IFERROR('HISTORICAL(FS)'!G34/SUM('HISTORICAL(FS)'!G50:G51),0) -> 0.055143844 | H23: =IFERROR('HISTORICAL(FS)'!H34/SUM('HISTORICAL(FS)'!H50:H51),0) -> 0.10789524 | I23: =IFERROR('HISTORICAL(FS)'!I34/SUM('HISTORICAL(FS)'!I50:I51),0) -> 0.35344508 | J23: =IFERROR('HISTORICAL(FS)'!J34/SUM('HISTORICAL(FS)'!J50:J51),0) -> 0.063119494 | ... L23: =IFERROR('HISTORICAL(FS)'!L34/SUM('HISTORICAL(FS)'!L50:L51),0) -> 0.025195671 | N23: =IFERROR(AVERAGE(C23:L23),0) -> 0.058140785 | O23: =IFERROR(MEDIAN(C23:L23),0) -> 0.059131669
B24: Self Sustained Growth Rate | C24: =IFERROR('Ratio Analysis'!C22*'Ratio Analysis'!C23,0) -> 0 | D24: =IFERROR('Ratio Analysis'!D22*'Ratio Analysis'!D23,0) -> 0 | E24: =IFERROR('Ratio Analysis'!E22*'Ratio Analysis'!E23,0) -> 0.093632527 | F24: =IFERROR('Ratio Analysis'!F22*'Ratio Analysis'!F23,0) -> 0.088638853 | G24: =IFERROR('Ratio Analysis'!G22*'Ratio Analysis'!G23,0) -> 0.039582447 | H24: =IFERROR('Ratio Analysis'!H22*'Ratio Analysis'!H23,0) -> 0.06756564 | I24: =IFERROR('Ratio Analysis'!I22*'Ratio Analysis'!I23,0) -> 0.29902351 | J24: =IFERROR('Ratio Analysis'!J22*'Ratio Analysis'!J23,0) -> 0.020469412 | ... L24: =IFERROR('Ratio Analysis'!L22*'Ratio Analysis'!L23,0) -> 0 | N24: =IFERROR(AVERAGE(C24:L24),0) -> 0.060891239 | O24: =IFERROR(MEDIAN(C24:L24),0) -> 0.03002593
B25: Interest Coverage Ratio | C25: =IFERROR(('HISTORICAL(FS)'!C19-'HISTORICAL(FS)'!C25)/'HISTORICAL(FS)'!C22,0) -> -1.4051206 | D25: =IFERROR(('HISTORICAL(FS)'!D19-'HISTORICAL(FS)'!D25)/'HISTORICAL(FS)'!D22,0) -> 1.4728816 | E25: =IFERROR(('HISTORICAL(FS)'!E19-'HISTORICAL(FS)'!E25)/'HISTORICAL(FS)'!E22,0) -> 2.8766706 | F25: =IFERROR(('HISTORICAL(FS)'!F19-'HISTORICAL(FS)'!F25)/'HISTORICAL(FS)'!F22,0) -> 2.868943 | G25: =IFERROR(('HISTORICAL(FS)'!G19-'HISTORICAL(FS)'!G25)/'HISTORICAL(FS)'!G22,0) -> 1.1976343 | H25: =IFERROR(('HISTORICAL(FS)'!H19-'HISTORICAL(FS)'!H25)/'HISTORICAL(FS)'!H22,0) -> 2.796297 | I25: =IFERROR(('HISTORICAL(FS)'!I19-'HISTORICAL(FS)'!I25)/'HISTORICAL(FS)'!I22,0) -> 9.9573578 | J25: =IFERROR(('HISTORICAL(FS)'!J19-'HISTORICAL(FS)'!J25)/'HISTORICAL(FS)'!J22,0) -> 3.6459841 | ... L25: =IFERROR(('HISTORICAL(FS)'!L19-'HISTORICAL(FS)'!L25)/'HISTORICAL(FS)'!L22,0) -> 2.0265933 | N25: =IFERROR(AVERAGE(C25:L25),0) -> 2.7084347 | O25: =IFERROR(MEDIAN(C25:L25),0) -> 2.4114451
B27: Debtor Turnover Ratio | C27: =IFERROR('HISTORICAL(FS)'!C7/'HISTORICAL(FS)'!C62,0) -> 8.4504277 | D27: =IFERROR('HISTORICAL(FS)'!D7/'HISTORICAL(FS)'!D62,0) -> 9.6919966 | E27: =IFERROR('HISTORICAL(FS)'!E7/'HISTORICAL(FS)'!E62,0) -> 9.9270163 | F27: =IFERROR('HISTORICAL(FS)'!F7/'HISTORICAL(FS)'!F62,0) -> 13.349335 | G27: =IFERROR('HISTORICAL(FS)'!G7/'HISTORICAL(FS)'!G62,0) -> 17.732181 | H27: =IFERROR('HISTORICAL(FS)'!H7/'HISTORICAL(FS)'!H62,0) -> 16.402518 | I27: =IFERROR('HISTORICAL(FS)'!I7/'HISTORICAL(FS)'!I62,0) -> 19.92084 | J27: =IFERROR('HISTORICAL(FS)'!J7/'HISTORICAL(FS)'!J62,0) -> 29.471432 | ... L27: =IFERROR('HISTORICAL(FS)'!L7/'HISTORICAL(FS)'!L62,0) -> 41.547532 | N27: =IFERROR(AVERAGE(C27:L27),0) -> 20.30814 | O27: =IFERROR(MEDIAN(C27:L27),0) -> 17.06735
B28: Creditor Turnover Ratio | C28: =IFERROR('HISTORICAL(FS)'!C7/'HISTORICAL(FS)'!C53,0) -> 1.9928798 | D28: =IFERROR('HISTORICAL(FS)'!D7/'HISTORICAL(FS)'!D53,0) -> 2.1757736 | E28: =IFERROR('HISTORICAL(FS)'!E7/'HISTORICAL(FS)'!E53,0) -> 2.2125526 | F28: =IFERROR('HISTORICAL(FS)'!F7/'HISTORICAL(FS)'!F53,0) -> 2.5014063 | G28: =IFERROR('HISTORICAL(FS)'!G7/'HISTORICAL(FS)'!G53,0) -> 2.359989 | H28: =IFERROR('HISTORICAL(FS)'!H7/'HISTORICAL(FS)'!H53,0) -> 1.9277973 | I28: =IFERROR('HISTORICAL(FS)'!I7/'HISTORICAL(FS)'!I53,0) -> 2.6397571 | J28: =IFERROR('HISTORICAL(FS)'!J7/'HISTORICAL(FS)'!J53,0) -> 2.4979585 | ... L28: =IFERROR('HISTORICAL(FS)'!L7/'HISTORICAL(FS)'!L53,0) -> 2.4421459 | N28: =IFERROR(AVERAGE(C28:L28),0) -> 2.329111 | O28: =IFERROR(MEDIAN(C28:L28),0) -> 2.4010674
B29: Inventory Turnover | C29: =IFERROR('HISTORICAL(FS)'!C7/'HISTORICAL(FS)'!C63,0) -> 5.0948403 | D29: =IFERROR('HISTORICAL(FS)'!D7/'HISTORICAL(FS)'!D63,0) -> 4.527505 | E29: =IFERROR('HISTORICAL(FS)'!E7/'HISTORICAL(FS)'!E63,0) -> 4.3503193 | F29: =IFERROR('HISTORICAL(FS)'!F7/'HISTORICAL(FS)'!F63,0) -> 4.9806827 | G29: =IFERROR('HISTORICAL(FS)'!G7/'HISTORICAL(FS)'!G63,0) -> 4.5002385 | H29: =IFERROR('HISTORICAL(FS)'!H7/'HISTORICAL(FS)'!H63,0) -> 4.7023564 | I29: =IFERROR('HISTORICAL(FS)'!I7/'HISTORICAL(FS)'!I63,0) -> 4.996666 | J29: =IFERROR('HISTORICAL(FS)'!J7/'HISTORICAL(FS)'!J63,0) -> 4.4721348 | ... L29: =IFERROR('HISTORICAL(FS)'!L7/'HISTORICAL(FS)'!L63,0) -> 4.9011618 | N29: =IFERROR(AVERAGE(C29:L29),0) -> 4.7187874 | O29: =IFERROR(MEDIAN(C29:L29),0) -> 4.6821626
B30: Fixed Asset Turnover | C30: =IFERROR('HISTORICAL(FS)'!C7/'HISTORICAL(FS)'!C56,0) -> 1.4122584 | D30: =IFERROR('HISTORICAL(FS)'!D7/'HISTORICAL(FS)'!D56,0) -> 1.220559 | E30: =IFERROR('HISTORICAL(FS)'!E7/'HISTORICAL(FS)'!E56,0) -> 1.2824433 | F30: =IFERROR('HISTORICAL(FS)'!F7/'HISTORICAL(FS)'!F56,0) -> 1.2670088 | G30: =IFERROR('HISTORICAL(FS)'!G7/'HISTORICAL(FS)'!G56,0) -> 1.0391376 | H30: =IFERROR('HISTORICAL(FS)'!H7/'HISTORICAL(FS)'!H56,0) -> 1.1524743 | I30: =IFERROR('HISTORICAL(FS)'!I7/'HISTORICAL(FS)'!I56,0) -> 1.8303184 | J30: =IFERROR('HISTORICAL(FS)'!J7/'HISTORICAL(FS)'!J56,0) -> 1.6597345 | ... L30: =IFERROR('HISTORICAL(FS)'!L7/'HISTORICAL(FS)'!L56,0) -> 1.4481256 | N30: =IFERROR(AVERAGE(C30:L30),0) -> 1.3852037 | O30: =IFERROR(MEDIAN(C30:L30),0) -> 1.3473509
B31: Capital Turnover Ratio | C31: =IFERROR('HISTORICAL(FS)'!C7/SUM('HISTORICAL(FS)'!C50:C51),0) -> 2.3315521 | D31: =IFERROR('HISTORICAL(FS)'!D7/SUM('HISTORICAL(FS)'!D50:D51),0) -> 2.9693665 | E31: =IFERROR('HISTORICAL(FS)'!E7/SUM('HISTORICAL(FS)'!E50:E51),0) -> 2.0247711 | F31: =IFERROR('HISTORICAL(FS)'!F7/SUM('HISTORICAL(FS)'!F50:F51),0) -> 2.2875416 | G31: =IFERROR('HISTORICAL(FS)'!G7/SUM('HISTORICAL(FS)'!G50:G51),0) -> 1.9002947 | H31: =IFERROR('HISTORICAL(FS)'!H7/SUM('HISTORICAL(FS)'!H50:H51),0) -> 2.1077585 | I31: =IFERROR('HISTORICAL(FS)'!I7/SUM('HISTORICAL(FS)'!I50:I51),0) -> 2.1317082 | J31: =IFERROR('HISTORICAL(FS)'!J7/SUM('HISTORICAL(FS)'!J50:J51),0) -> 2.3607657 | ... L31: =IFERROR('HISTORICAL(FS)'!L7/SUM('HISTORICAL(FS)'!L50:L51),0) -> 2.3970977 | N31: =IFERROR(AVERAGE(C31:L31),0) -> 2.3000875 | O31: =IFERROR(MEDIAN(C31:L31),0) -> 2.3095469
B33: Debtor Days | C33: =IFERROR(365/C27,0) -> 43.19308 | D33: =IFERROR(365/D27,0) -> 37.659939 | E33: =IFERROR(365/E27,0) -> 36.768349 | F33: =IFERROR(365/F27,0) -> 27.342187 | G33: =IFERROR(365/G27,0) -> 20.584045 | H33: =IFERROR(365/H27,0) -> 22.252681 | I33: =IFERROR(365/I27,0) -> 18.322521 | J33: =IFERROR(365/J27,0) -> 12.384875 | ... L33: =IFERROR(365/L27,0) -> 8.7851187 | N33: =IFERROR(365/N27,0) -> 17.973089 | O33: =IFERROR(365/O27,0) -> 21.385863
B34: Payable Days | C34: =IFERROR(365/C28,0) -> 183.15204 | D34: =IFERROR(365/D28,0) -> 167.75643 | E34: =IFERROR(365/E28,0) -> 164.96783 | F34: =IFERROR(365/F28,0) -> 145.91792 | G34: =IFERROR(365/G28,0) -> 154.66174 | H34: =IFERROR(365/H28,0) -> 189.33526 | I34: =IFERROR(365/I28,0) -> 138.2703 | J34: =IFERROR(365/J28,0) -> 146.11932 | ... L34: =IFERROR(365/L28,0) -> 149.45872 | N34: =IFERROR(365/N28,0) -> 156.71215 | O34: =IFERROR(365/O28,0) -> 152.01572
B35: Inventory Days | C35: =IFERROR(365/C29,0) -> 71.641107 | D35: =IFERROR(365/D29,0) -> 80.618353 | E35: =IFERROR(365/E29,0) -> 83.901887 | F35: =IFERROR(365/F29,0) -> 73.283126 | G35: =IFERROR(365/G29,0) -> 81.106812 | H35: =IFERROR(365/H29,0) -> 77.620658 | I35: =IFERROR(365/I29,0) -> 73.048709 | J35: =IFERROR(365/J29,0) -> 81.616503 | ... L35: =IFERROR(365/L29,0) -> 74.472139 | N35: =IFERROR(365/N29,0) -> 77.350381 | O35: =IFERROR(365/O29,0) -> 77.95543
B36: Cash Conversion Cycle | C36: =IFERROR(SUM(C33+C35)-C34,0) -> -68.31785 | D36: =IFERROR(SUM(D33+D35)-D34,0) -> -49.478134 | E36: =IFERROR(SUM(E33+E35)-E34,0) -> -44.297593 | F36: =IFERROR(SUM(F33+F35)-F34,0) -> -45.292607 | G36: =IFERROR(SUM(G33+G35)-G34,0) -> -52.970883 | H36: =IFERROR(SUM(H33+H35)-H34,0) -> -89.461918 | I36: =IFERROR(SUM(I33+I35)-I34,0) -> -46.899069 | J36: =IFERROR(SUM(J33+J35)-J34,0) -> -52.117944 | ... L36: =IFERROR(SUM(L33+L35)-L34,0) -> -66.201461 | N36: =IFERROR(365/N30,0) -> 263.49915 | O36: =IFERROR(365/O30,0) -> 270.90197
B38: CFO/Sales | C38: =IFERROR('HISTORICAL(FS)'!#REF!/'HISTORICAL(FS)'!C7,0) -> 0 | D38: =IFERROR('HISTORICAL(FS)'!#REF!/'HISTORICAL(FS)'!D7,0) -> 0 | E38: =IFERROR('HISTORICAL(FS)'!#REF!/'HISTORICAL(FS)'!E7,0) -> 0 | F38: =IFERROR('HISTORICAL(FS)'!#REF!/'HISTORICAL(FS)'!F7,0) -> 0 | G38: =IFERROR('HISTORICAL(FS)'!#REF!/'HISTORICAL(FS)'!G7,0) -> 0 | H38: =IFERROR('HISTORICAL(FS)'!#REF!/'HISTORICAL(FS)'!H7,0) -> 0 | I38: =IFERROR('HISTORICAL(FS)'!#REF!/'HISTORICAL(FS)'!I7,0) -> 0 | J38: =IFERROR('HISTORICAL(FS)'!#REF!/'HISTORICAL(FS)'!J7,0) -> 0 | ... L38: =IFERROR('HISTORICAL(FS)'!#REF!/'HISTORICAL(FS)'!L7,0) -> 0 | N38: =IFERROR(AVERAGE(C38:L38),0) -> 0 | O38: =IFERROR(MEDIAN(C38:L38),0) -> 0
B39: CFO/Total Assets | C39: =IFERROR('HISTORICAL(FS)'!#REF!/'HISTORICAL(FS)'!C67,0) -> 0 | D39: =IFERROR('HISTORICAL(FS)'!#REF!/'HISTORICAL(FS)'!D67,0) -> 0 | E39: =IFERROR('HISTORICAL(FS)'!#REF!/'HISTORICAL(FS)'!E67,0) -> 0 | F39: =IFERROR('HISTORICAL(FS)'!#REF!/'HISTORICAL(FS)'!F67,0) -> 0 | G39: =IFERROR('HISTORICAL(FS)'!#REF!/'HISTORICAL(FS)'!G67,0) -> 0 | H39: =IFERROR('HISTORICAL(FS)'!#REF!/'HISTORICAL(FS)'!H67,0) -> 0 | I39: =IFERROR('HISTORICAL(FS)'!#REF!/'HISTORICAL(FS)'!I67,0) -> 0 | J39: =IFERROR('HISTORICAL(FS)'!#REF!/'HISTORICAL(FS)'!J67,0) -> 0 | ... L39: =IFERROR('HISTORICAL(FS)'!#REF!/'HISTORICAL(FS)'!L67,0) -> 0 | N39: =IFERROR(AVERAGE(C39:L39),0) -> 0 | O39: =IFERROR(MEDIAN(C39:L39),0) -> 0
B40: CFO/Total Debt | C40: =IFERROR('HISTORICAL(FS)'!#REF!/'HISTORICAL(FS)'!C52,0) -> 0 | D40: =IFERROR('HISTORICAL(FS)'!#REF!/'HISTORICAL(FS)'!D52,0) -> 0 | E40: =IFERROR('HISTORICAL(FS)'!#REF!/'HISTORICAL(FS)'!E52,0) -> 0 | F40: =IFERROR('HISTORICAL(FS)'!#REF!/'HISTORICAL(FS)'!F52,0) -> 0 | G40: =IFERROR('HISTORICAL(FS)'!#REF!/'HISTORICAL(FS)'!G52,0) -> 0 | H40: =IFERROR('HISTORICAL(FS)'!#REF!/'HISTORICAL(FS)'!H52,0) -> 0 | I40: =IFERROR('HISTORICAL(FS)'!#REF!/'HISTORICAL(FS)'!I52,0) -> 0 | J40: =IFERROR('HISTORICAL(FS)'!#REF!/'HISTORICAL(FS)'!J52,0) -> 0 | ... L40: =IFERROR('HISTORICAL(FS)'!#REF!/'HISTORICAL(FS)'!L52,0) -> 0 | N40: =IFERROR(AVERAGE(C40:L40),0) -> 0 | O40: =IFERROR(MEDIAN(C40:L40),0) -> 0

Sheet Forecasting 
B3: TATA STEEL LTD - FORECASTING
B6: TATA STEEL LTD - Sales Forecasting | G6: TATA STEEL LTD - EBITDA Forecasting | L6: TATA STEEL LTD - EBIT Forecasting | Q6: TATA STEEL LTD - Net Profit Forecasting
B7: Year Weight | C7: Year | D7: Sales | E7: Sales Growth | G7: Year Weight | H7: Year | I7: EBITDA | J7: EBITDA Growth | L7: Year Weight | M7: Year | N7: EBIT | O7: EBIT Growth | Q7: Year Weight | R7: Year | S7: Net Profit | T7: Net Profit Growth
B8: 1 | C8: 2016 | D8: 101965 | G8: 1 | H8: 2016 | I8: -625.24 | L8: 1 | M8: 2016 | N8: -10153 | Q8: 1 | R8: 2016 | S8: -10842.96
B9: =1+B8 -> 2 | C9: =1+C8 -> 2017 | D9: 112299 | E9: =IFERROR(D9/D8-1,0) -> 0.1013485 | G9: =1+G8 -> 2 | H9: =1+H8 -> 2017 | I9: 13143.63 | J9: =IFERROR(I9/I8-1,0) -> -22.021736 | L9: 2 | M9: 2017 | N9: 2398.55 | O9: =IFERROR(N9/N8-1,0) -> -1.2362405 | Q9: =1+Q8 -> 2 | R9: =1+R8 -> 2017 | S9: -379.46 | T9: =IFERROR(S9/S8-1,0) -> -0.96500402
B10: =1+B9 -> 3 | C10: =1+C9 -> 2018 | D10: 123249 | E10: =IFERROR(D10/D9-1,0) -> 0.097507547 | G10: =1+G9 -> 3 | H10: =1+H9 -> 2018 | I10: 21433.19 | J10: =IFERROR(I10/I9-1,0) -> 0.6306903 | L10: 3 | M10: 2018 | N10: 10236.75 | O10: =IFERROR(N10/N9-1,0) -> 3.267891 | Q10: =1+Q9 -> 3 | R10: =1+R9 -> 2018 | S10: 6844.42 | T10: =IFERROR(S10/S9-1,0) -> -19.037263
B11: =1+B10 -> 4 | C11: =1+C10 -> 2019 | D11: 157669 | E11: =IFERROR(D11/D10-1,0) -> 0.27927204 | G11: =1+G10 -> 4 | H11: =1+H10 -> 2019 | I11: 29318.22 | J11: =IFERROR(I11/I10-1,0) -> 0.36788877 | L11: 4 | M11: 2019 | N11: 14316.29 | O11: =IFERROR(N11/N10-1,0) -> 0.39851906 | Q11: =1+Q10 -> 4 | R11: =1+R10 -> 2019 | S11: 7597.86 | T11: =IFERROR(S11/S10-1,0) -> 0.11008091
B12: =1+B11 -> 5 | C12: =1+C11 -> 2020 | D12: 139817 | E12: =IFERROR(D12/D11-1,0) -> -0.11322454 | G12: =1+G11 -> 5 | H12: =1+H11 -> 2020 | I12: 17463.06 | J12: =IFERROR(I12/I11-1,0) -> -0.40436152 | L12: 5 | M12: 2020 | N12: 1488.87 | O12: =IFERROR(N12/N11-1,0) -> -0.89600169 | Q12: =1+Q11 -> 5 | R12: =1+R11 -> 2020 | S12: 4057.28 | T12: =IFERROR(S12/S11-1,0) -> -0.465997
B13: =1+B12 -> 6 | C13: =1+C12 -> 2021 | D13: 156477 | E13: =IFERROR(D13/D12-1,0) -> 0.11915575 | G13: =1+G12 -> 6 | H13: =1+H12 -> 2021 | I13: 30504.26 | J13: =IFERROR(I13/I12-1,0) -> 0.74678779 | L13: 6 | M13: 2021 | N13: 13663.91 | O13: =IFERROR(N13/N12-1,0) -> 8.1773694 | Q13: =1+Q12 -> 6 | R13: =1+R12 -> 2021 | S13: 8010.01 | T13: =IFERROR(S13/S12-1,0) -> 0.9742315
B14: =1+B13 -> 7 | C14: =1+C13 -> 2022 | D14: 243959 | E14: =IFERROR(D14/D13-1,0) -> 0.55907258 | G14: =1+G13 -> 7 | H14: =1+H13 -> 2022 | I14: 63489.95 | J14: =IFERROR(I14/I13-1,0) -> 1.081347 | L14: 7 | M14: 2022 | N14: 48926.88 | O14: =IFERROR(N14/N13-1,0) -> 2.5807379 | Q14: =1+Q13 -> 7 | R14: =1+R13 -> 2022 | S14: 40449.33 | T14: =IFERROR(S14/S13-1,0) -> 4.0498476
B15: =1+B14 -> 8 | C15: =1+C14 -> 2023 | D15: 243353 | E15: =IFERROR(D15/D14-1,0) -> -0.002484024 | G15: =1+G14 -> 8 | H15: =1+H14 -> 2023 | I15: 32300.16 | J15: =IFERROR(I15/I14-1,0) -> -0.49125555 | L15: 8 | M15: 2023 | N15: 16666.26 | O15: =IFERROR(N15/N14-1,0) -> -0.65936393 | Q15: =1+Q14 -> 8 | R15: =1+R14 -> 2023 | S15: 6506.49 | T15: =IFERROR(S15/S14-1,0) -> -0.83914468
B16: =1+B15 -> 9 | C16: =1+C15 -> 2024 | D16: 229171 | E16: =IFERROR(D16/D15-1,0) -> -0.058277482 | G16: =1+G15 -> 9 | H16: =1+H15 -> 2024 | I16: 22247.92 | J16: =IFERROR(I16/I15-1,0) -> -0.31121332 | L16: 9 | M16: 2024 | N16: 4858.19 | O16: =IFERROR(N16/N15-1,0) -> -0.70850149 | Q16: =1+Q15 -> 9 | R16: =1+R15 -> 2024 | S16: 1095.62 | T16: =IFERROR(S16/S15-1,0) -> -0.83161121
B17: =1+B16 -> 10 | C17: =1+C16 -> 2025 | D17: 218543 | E17: =IFERROR(D17/D16-1,0) -> -0.04637585 | G17: =1+G16 -> 10 | H17: =1+H16 -> 2025 | I17: 25298.45 | J17: =IFERROR(I17/I16-1,0) -> 0.13711529 | L17: 10 | M17: 2025 | N17: 7536.17 | O17: =IFERROR(N17/N16-1,0) -> 0.55122998 | Q17: =1+Q16 -> 10 | R17: =1+R16 -> 2025 | S17: 2297.08 | T17: =IFERROR(S17/S16-1,0) -> 1.0966028
B18: =1+B17 -> 11 | C18: =1+C17 -> 2026 | D18: =FORECAST(B18,D8:D17,B8:B17) -> 264095.4 | E18: =IFERROR(D18/D17-1,0) -> 0.20843678 | G18: =1+G17 -> 11 | H18: =1+H17 -> 2026 | I18: =FORECAST(G18,I8:I17,G8:G17) -> 41021.843 | J18: =IFERROR(I18/I17-1,0) -> 0.62151605 | L18: 11 | M18: 2026 | N18: =FORECAST(L18,N8:N17,L8:L17) -> 21813.033 | O18: =IFERROR(N18/N17-1,0) -> 1.8944454 | Q18: =1+Q17 -> 11 | R18: =1+R17 -> 2026 | S18: =FORECAST(Q18,S8:S17,Q8:Q17) -> 14210.347 | T18: =IFERROR(S18/S17-1,0) -> 5.1862658
B19: =1+B18 -> 12 | C19: =1+C18 -> 2027 | D19: =FORECAST(B19,D9:D18,B9:B18) -> 281824.09 | E19: =IFERROR(D19/D18-1,0) -> 0.067129883 | G19: =1+G18 -> 12 | H19: =1+H18 -> 2027 | I19: =FORECAST(G19,I9:I18,G9:G18) -> 40292.276 | J19: =IFERROR(I19/I18-1,0) -> -0.017784841 | L19: 12 | M19: 2027 | N19: =FORECAST(L19,N9:N18,L9:L18) -> 20501.521 | O19: =IFERROR(N19/N18-1,0) -> -0.060125138 | Q19: =1+Q18 -> 12 | R19: =1+R18 -> 2027 | S19: =FORECAST(Q19,S9:S18,Q9:Q18) -> 12627.319 | T19: =IFERROR(S19/S18-1,0) -> -0.1113997
B20: =1+B19 -> 13 | C20: =1+C19 -> 2028 | D20: =FORECAST(B20,D10:D19,B10:B19) -> 298591.3 | E20: =IFERROR(D20/D19-1,0) -> 0.059495306 | G20: =1+G19 -> 13 | H20: =1+H19 -> 2028 | I20: =FORECAST(G20,I10:I19,G10:G19) -> 40166.109 | J20: =IFERROR(I20/I19-1,0) -> -0.0031313004 | L20: 13 | M20: 2028 | N20: =FORECAST(L20,N10:N19,L10:L19) -> 19881.416 | O20: =IFERROR(N20/N19-1,0) -> -0.030246784 | Q20: =1+Q19 -> 13 | R20: =1+R19 -> 2028 | S20: =FORECAST(Q20,S10:S19,Q10:Q19) -> 11531.125 | T20: =IFERROR(S20/S19-1,0) -> -0.086811269
B21: =1+B20 -> 14 | C21: =1+C20 -> 2029 | D21: =FORECAST(B21,D11:D20,B11:B20) -> 313683.73 | E21: =IFERROR(D21/D20-1,0) -> 0.050545417 | G21: =1+G20 -> 14 | H21: =1+H20 -> 2029 | I21: =FORECAST(G21,I11:I20,G11:G20) -> 40390.114 | J21: =IFERROR(I21/I20-1,0) -> 0.0055769782 | L21: 14 | M21: 2029 | N21: =FORECAST(L21,N11:N20,L11:L20) -> 19896.591 | O21: =IFERROR(N21/N20-1,0) -> 0.00076326609 | Q21: =1+Q20 -> 14 | R21: =1+R20 -> 2029 | S21: =FORECAST(Q21,S11:S20,Q11:Q20) -> 11055.704 | T21: =IFERROR(S21/S20-1,0) -> -0.04122942
B22: =1+B21 -> 15 | C22: =1+C21 -> 2030 | D22: =FORECAST(B22,D12:D21,B12:B21) -> 332302.3 | E22: =IFERROR(D22/D21-1,0) -> 0.059354595 | G22: =1+G21 -> 15 | H22: =1+H21 -> 2030 | I22: =FORECAST(G22,I12:I21,G12:G21) -> 41557.535 | J22: =IFERROR(I22/I21-1,0) -> 0.028903636 | L22: 15 | M22: 2030 | N22: =FORECAST(L22,N12:N21,L12:L21) -> 20362.735 | O22: =IFERROR(N22/N21-1,0) -> 0.023428352 | Q22: =1+Q21 -> 15 | R22: =1+R21 -> 2030 | S22: =FORECAST(Q22,S12:S21,Q12:Q21) -> 10278.584 | T22: =IFERROR(S22/S21-1,0) -> -0.070291314

Sheet DCF Modelling(WACC)
B3: WACC Calculation of TATA STEEL LTD
B6: Weighted Average Cost of Capital
B8: All figures are in INR unless stated otherwise.
B10: Peer comps
I11: Debt / | J11: Debt / | K11: Levered | L11: Unlevered
B12: Name of the comp | D12: Country | E12: Total Debt | G12: Total Equity | H12: Tax Rate1 | I12: Equity | J12: Capital | K12: Beta 2 | L12: Beta 3
B14: JSW Steel | D14: India | E14: 101107 | G14: 285152.14 | H14: 0.3 | I14: =E14/G14 -> 0.35457212 | J14: =E14/(E14+G14) -> 0.2617595 | K14: 1.18 | L14: =K14/(1+(1-H14)*I14) -> 0.94536095
B15: Tata Steel | D15: India | E15: 95643.13 | G15: 243928.11 | H15: 0.3 | I15: =E15/G15 -> 0.39209556 | J15: =E15/(E15+G15) -> 0.28165851 | K15: ='Beta Regression'!J8 -> 1.2983571 | L15: =K15/(1+(1-H15)*I15) -> 1.0187452
B16: Jindal Steel | D16: India | E16: 19155.98 | G16: 118126.13 | H16: 0.3 | I16: =E16/G16 -> 0.16216548 | J16: =E16/(E16+G16) -> 0.13953734 | K16: 1.18 | L16: =K16/(1+(1-H16)*I16) -> 1.0597065
B17: Jindal Stain. | D17: India | E17: 6861.97 | G17: 60273.39 | H17: 0.3 | I17: =E17/G17 -> 0.11384742 | J17: =E17/(E17+G17) -> 0.10221097 | K17: 1.29 | L17: =K17/(1+(1-H17)*I17) -> 1.1947839
B18: NMDC Steel | D18: India | E18: 5309.93 | G18: 10834.49 | H18: 0.3 | I18: =E18/G18 -> 0.49009506 | J18: =E18/(E18+G18) -> 0.32890187 | K18: 1.99 | L18: =K18/(1+(1-H18)*I18) -> 1.4816838
G20: Average | H20: =AVERAGE(H14:H18) -> 0.3 | I20: =AVERAGE(I14:I18) -> 0.30255513 | J20: =AVERAGE(J14:J18) -> 0.22281364 | K20: =AVERAGE(K14:K18) -> 1.3876714 | L20: =AVERAGE(L14:L18) -> 1.1400561
G21: Median | H21: =MEDIAN(H14:H18) -> 0.3 | I21: =MEDIAN(I14:I18) -> 0.35457212 | J21: =MEDIAN(J14:J18) -> 0.2617595 | K21: =MEDIAN(K14:K18) -> 1.29 | L21: =MEDIAN(L14:L18) -> 1.0597065
B24: Cost of Debt | H24: Cost of Equity
B26: Pre-Tax Cost of Debt | E26: =7163/95643.13 -> 0.07489299
B27: Tax Rate | E27: =H14 -> 0.3 | H27: Risk Free Rate | L27: 0.0671
B28: After Tax Cost of Debt | E28: =E26*(1-E27) -> 0.052425093 | H28: Equity Risk Premium | L28: ='return on market'!G8-'DCF Modelling(WACC)'!L27 -> 0.084392308
E29: p;l | H29: Levered Beta 4 | L29: ='Beta Regression'!J14 -> 1.2237678
H30: Cost of Equity | L30: =L27+L28*L29 -> 0.17037659
B33: Capital Structure | H33: Levered Beta
D35: Current | E35: Target | H35: Comps Median Unlevered Beta | L35: =L21 -> 1.0597065
B36: Total Debt | C36: =E15 -> 95643.13 | D36: =C36/$C$38 -> 0.28165851 | E36: =J20 -> 0.22281364 | H36: Target Debt/Equity | L36: =E40 -> 0.28669268
B37: Market Capitalization | C37: =G15 -> 243928.11 | D37: =C37/$C$38 -> 0.71834149 | E37: =E38-E36 -> 0.77718636 | H37: Tax Rate | L37: =H18 -> 0.3
B38: Total Capital | C38: =SUM(C36:C37) -> 339571.24 | D38: =C38/$C$38 -> 1 | E38: 1 | H38: Levered Beta | L38: =L35*(1+(1-L37)*L36) -> 1.2723736
B40: Debt/Equity | D40: =D36/D37 -> 0.39209556 | E40: =E36/E37 -> 0.28669268 | H40: Weighted Average Cost of Capital
B42: Notes:
B43: 1. Tax Rate considered as Marginal Tax Rate for the country | H43: Cost of Equity | L43: =L30 -> 0.17037659
B44: 2. Levered beta is bases on 5 year monthly data | H44: Equity Weight | L44: =E37 -> 0.77718636
B45: 3.Unlevered Beta=Levered Beta/(1+(1-Tax Rate )*Debt/Equity)
B46: 4. Levered Beta= Unlevered Beta*(1+(1-Tax Rate )*Debt/Equity | H46: Cost of Debt | L46: =E28 -> 0.052425093
H47: Debt Weight | L47: =E36 -> 0.22281364
H49: WACC | L49: =(L43*L44)+(L46*L47) -> 0.14409539

Sheet return on market
B2: Return on Market
B4: Year | C4: Annual
B5: 2000 | C5: -0.1465
B6: 2001 | C6: -0.1618 | E6: Average Return | G6: =AVERAGE(C5:C30) -> 0.15149231
B7: 2002 | C7: 0.0325 | E7: Divident Yield | G7: 1.28% 1
B8: 2003 | C8: 0.719 | E8: Total Market Return | G8: =SUM(G6:G7) -> 0.15149231
B9: 2004 | C9: 0.1068
B10: 2005 | C10: 0.3634
B11: 2006 | C11: 0.3983
B12: 2007 | C12: 0.5477
B13: 2008 | C13: -0.5179
B14: 2009 | C14: 0.7576
B15: 2010 | C15: 0.1795
B16: 2011 | C16: -0.2462
B17: 2012 | C17: 0.277
B18: 2013 | C18: 0.0676
B19: 2014 | C19: 0.3139
B20: 2015 | C20: -0.0406
... B30: 2025 | C30: 0.1051

Sheet pre-tax cost of debt
C2: TATA STEEL LTD
C3: Calcuation of Pre- Tax cost of Debt
C5: Annual interest | E5: 7163
C6: Total Debt | E6: 95643.13
C8: Pre-Tax cost of Debt | E8: =E5/E6 -> 0.07489299

Sheet Beta Regression
B2: TATA STEEL LTD - Beta Regression
B4: Regreesion Beta - 2 Years Weekly
B6: Tata Motor Weekly Returns | F6: Nifty 50 Returns | I6: Beta Drifting
B8: Date | C8: Closing Price | D8: Returns | F8: Closing Price | G8: Returns | I8: Levered Raw Beta | J8: =M11 -> 1.2983571 | L8: Beta 1 | M8: =SLOPE(D10:D114,G10:G114) -> 1.2983713
B9: Mar 20, 2026 | C9: 196.7 | F9: 23114.5 | I9: Raw Beta Weight | J9: 0.75 | L9: Beta 2 | M9: =_xlfn.COVARIANCE.S(D10:D114,G10:G114)/_xlfn.VAR.S(G10:G114) -> 1.2983713
B10: Mar 16, 2026 | C10: 196.7 | D10: =C10/C9-1 -> 0 | F10: 23114.5 | G10: =F10/F9-1 -> 0
B11: Mar 9, 2026 | C11: 183.4 | D11: =C11/C10-1 -> -0.067615658 | F11: 23151.1 | G11: =F11/F10-1 -> 0.0015834217 | I11: Market Beta | J11: 1 | L11: Beta 3 | M11: =J34 -> 1.2983571
B12: Mar 2, 2026 | C12: 198.5 | D12: =C12/C11-1 -> 0.082333697 | F12: 24450.45 | G12: =F12/F11-1 -> 0.056124763 | I12: Market Beta Weight | J12: 0.25
B13: Feb 23, 2026 | C13: 212.35 | D13: =C13/C12-1 -> 0.0697733 | F13: 25178.65 | G13: =F13/F12-1 -> 0.029782683
B14: Feb 16, 2026 | C14: 208.25 | D14: =C14/C13-1 -> -0.019307747 | F14: 25571.25 | G14: =F14/F13-1 -> 0.015592575 | I14: Adjusted Beta | J14: =(J8*J9)+(J11*J12) -> 1.2237678
B15: Feb 9, 2026 | C15: 203.2 | D15: =C15/C14-1 -> -0.0242497 | F15: 25471.1 | G15: =F15/F14-1 -> -0.0039165078
B16: Feb 2, 2026 | C16: 197.05 | D16: =C16/C15-1 -> -0.030265748 | F16: 25693.7 | G16: =F16/F15-1 -> 0.0087393163
B17: Jan 26, 2026 | C17: 185.6 | D17: =C17/C16-1 -> -0.058107079 | F17: 24825.45 | G17: =F17/F16-1 -> -0.03379233 | I17: SUMMARY OUTPUT
B18: Jan 19, 2026 | C18: 187.55 | D18: =C18/C17-1 -> 0.010506466 | F18: 25048.65 | G18: =F18/F17-1 -> 0.0089907736
B19: Jan 12, 2026 | C19: 188.1 | D19: =C19/C18-1 -> 0.0029325513 | F19: 25694.35 | G19: =F19/F18-1 -> 0.025777836 | I19: Regression Statistics
B20: Jan 5, 2026 | C20: 178.3 | D20: =C20/C19-1 -> -0.052099947 | F20: 25683.3 | G20: =F20/F19-1 -> -0.00043005563 | I20: Multiple R | J20: 0.60853044
B21: Dec 29, 2025 | C21: 182.85 | D21: =C21/C20-1 -> 0.025518789 | F21: 26328.55 | G21: =F21/F20-1 -> 0.025123329 | I21: R Square | J21: 0.3703093
B22: Dec 22, 2025 | C22: 169.15 | D22: =C22/C21-1 -> -0.074924802 | F22: 26042.3 | G22: =F22/F21-1 -> -0.010872228 | I22: Adjusted R Square | J22: 0.36413586
B23: Dec 15, 2025 | C23: 168.65 | D23: =C23/C22-1 -> -0.0029559563 | F23: 25966.4 | G23: =F23/F22-1 -> -0.0029144891 | I23: Standard Error | J23: 0.030825703
B24: Dec 8, 2025 | C24: 171.9 | D24: =C24/C23-1 -> 0.019270679 | F24: 26046.95 | G24: =F24/F23-1 -> 0.0031020858 | I24: Observations | J24: 104
B25: Dec 1, 2025 | C25: 167.1 | D25: =C25/C24-1 -> -0.027923211 | F25: 26186.45 | G25: =F25/F24-1 -> 0.0053557134
B26: Nov 24, 2025 | C26: 167.85 | D26: =C26/C25-1 -> 0.0044883303 | F26: 26202.95 | G26: =F26/F25-1 -> 0.00063009686 | I26: ANOVA
B27: Nov 17, 2025 | C27: 168 | D27: =C27/C26-1 -> 0.00089365505 | F27: 26068.15 | G27: =F27/F26-1 -> -0.0051444589 | J27: df | K27: SS | L27: MS | M27: F | N27: Significance F
B28: Nov 10, 2025 | C28: 174.15 | D28: =C28/C27-1 -> 0.036607143 | F28: 25910.05 | G28: =F28/F27-1 -> -0.0060648723 | I28: Regression | J28: 1 | K28: 0.056998507 | L28: 0.056998507 | M28: 59.984288 | N28: 7.2601811e-12
B29: Nov 3, 2025 | C29: 181.45 | D29: =C29/C28-1 -> 0.041917887 | F29: 25492.3 | G29: =F29/F28-1 -> -0.016123087 | I29: Residual | J29: 102 | K29: 0.096922842 | L29: 0.00095022394
B30: Oct 27, 2025 | C30: 182.95 | D30: =C30/C29-1 -> 0.0082667401 | F30: 25722.1 | G30: =F30/F29-1 -> 0.0090144867 | I30: Total | J30: 103 | K30: 0.15392135
B31: Oct 20, 2025 | C31: 174.5 | D31: =C31/C30-1 -> -0.046187483 | F31: 25795.15 | G31: =F31/F30-1 -> 0.0028399703
B32: Oct 13, 2025 | C32: 172.25 | D32: =C32/C31-1 -> -0.012893983 | F32: 25709.85 | G32: =F32/F31-1 -> -0.0033068232 | J32: Coefficients | K32: Standard Error | L32: t Stat | M32: P-value | N32: Lower 95% | O32: Upper 95% | P32: Lower 95.0% | Q32: Upper 95.0%
B33: Oct 6, 2025 | C33: 173.8 | D33: =C33/C32-1 -> 0.0089985486 | F33: 25285.35 | G33: =F33/F32-1 -> -0.016511182 | I33: Intercept | J33: -0.0017967523 | K33: 0.0030230504 | L33: -0.59435077 | M33: 0.55359356 | N33: -0.0077929584 | O33: 0.0041994538 | P33: -0.0077929584 | Q33: 0.0041994538
B34: Sep 29, 2025 | C34: 173.2 | D34: =C34/C33-1 -> -0.003452244 | F34: 24894.25 | G34: =F34/F33-1 -> -0.015467454 | I34: 0 | J34: 1.2983571 | K34: 0.16763913 | L34: 7.7449524 | M34: 7.2601811e-12 | N34: 0.96584565 | O34: 1.6308685 | P34: 0.96584565 | Q34: 1.6308685
B35: Sep 22, 2025 | C35: 167.45 | D35: =C35/C34-1 -> -0.033198614 | F35: 24654.7 | G35: =F35/F34-1 -> -0.009622704
B36: Sep 15, 2025 | C36: 171.5 | D36: =C36/C35-1 -> 0.024186324 | F36: 25327.05 | G36: =F36/F35-1 -> 0.027270662
B37: Sep 8, 2025 | C37: 169.8 | D37: =C37/C36-1 -> -0.0099125364 | F37: 25114 | G37: =F37/F36-1 -> -0.0084119548
B38: Sep 1, 2025 | C38: 167.65 | D38: =C38/C37-1 -> -0.012661955 | F38: 24741 | G38: =F38/F37-1 -> -0.014852274
B39: Aug 25, 2025 | C39: 154.45 | D39: =C39/C38-1 -> -0.078735461 | F39: 24426.85 | G39: =F39/F38-1 -> -0.012697547
B40: Aug 18, 2025 | C40: 158.55 | D40: =C40/C39-1 -> 0.026545808 | F40: 24870.1 | G40: =F40/F39-1 -> 0.018146016
B41: Aug 11, 2025 | C41: 155.3 | D41: =C41/C40-1 -> -0.020498266 | F41: 24631.3 | G41: =F41/F40-1 -> -0.0096018914
B42: Aug 4, 2025 | C42: 158 | D42: =C42/C41-1 -> 0.017385705 | F42: 24363.3 | G42: =F42/F41-1 -> -0.010880465
B43: Jul 28, 2025 | C43: 153 | D43: =C43/C42-1 -> -0.03164557 | F43: 24565.35 | G43: =F43/F42-1 -> 0.0082932115
B44: Jul 21, 2025 | C44: 161.4 | D44: =C44/C43-1 -> 0.054901961 | F44: 24837 | G44: =F44/F43-1 -> 0.011058259
B45: Jul 14, 2025 | C45: 162.5 | D45: =C45/C44-1 -> 0.0068153656 | F45: 24968.4 | G45: =F45/F44-1 -> 0.005290494
B46: Jul 7, 2025 | C46: 159.85 | D46: =C46/C45-1 -> -0.016307692 | F46: 25149.85 | G46: =F46/F45-1 -> 0.0072671857
... B114: Mar 18, 2024 | C114: 145.56 | D114: =C114/C113-1 -> -0.02531137 | F114: 22096.75 | G114: =F114/F113-1 -> -0.010308193

Sheet beta comparison
B2: .No. | C2: Name | D2: CMP Rs. | E2: Mar Cap Rs.Cr. | F2: Debt Rs.Cr. | G2: Debt / Eq
B3: 1 | C3: JSW Steel | D3: 1166.05 | E3: 285152.14 | F3: 101107 | G3: 1.22
B4: 2 | C4: Tata Steel | D4: 195.4 | E4: 243928.11 | F4: 95643.13 | G4: 1.01
B5: 3 | C5: Jindal Steel | D5: 1158 | E5: 118126.13 | F5: 19155.98 | G5: 0.39
B6: 5 | C6: Jindal Stain. | D6: 731.1 | E6: 60273.39 | F6: 6861.97 | G6: 0.38
B7: 7 | C7: NMDC Steel | D7: 36.97 | E7: 10834.49 | F7: 5309.93 | G7: 0.41

Sheet IG raw Data
B3: BALANCE SHEET DATA FOR THE CALCULATION OF INTRINSIC GROWTH OF TATA STEEL LTTD
B5: Particulars | C5: 42430 | D5: 42795 | E5: 43160 | F5: 43525 | G5: 43891 | H5: 44256 | I5: 44621 | J5: 44986 | K5: 45352 | L5: 45717
B7: Equity Capital | C7: 970 | D7: 970 | E7: 1145 | F7: 1145 | G7: 1145 | H7: 1198 | I7: 1221 | J7: 1221 | K7: 1247 | L7: 1247
B8: Reserves | C8: 42762 | D8: 36849 | E8: 59726 | F8: 67780 | G8: 72431 | H8: 73041 | I8: 113222 | J8: 101861 | K8: 90788 | L8: 89922
B9: Borrowings -
B10: Long term Borrowings | C10: 64873 | D10: 64022 | E10: 72789 | F10: 80343 | G10: 94105 | H10: 65698 | I10: 44764 | J10: 51446 | K10: 51577 | L10: 68552
B11: Short term Borrowings | C11: 15722 | D11: 18328 | E11: 15885 | F11: 10802 | G11: 19184 | H11: 14969 | I11: 24065 | J11: 26571 | K11: 29997 | L11: 20412
B12: Lease Liabilities | C12: 0 | D12: 0 | E12: 0 | F12: 0 | G12: 0 | H12: 7834 | I12: 6733 | J12: 6875 | K12: 5508 | L12: 5837
B13: Preference Capital | C13: 0 | D13: 0 | E13: 20 | F13: 13 | G13: 0 | H13: 0 | I13: 0 | J13: 0 | K13: 0 | L13: 0
B14: Other Borrowings | C14: 1392 | D14: 664 | E14: 3453 | F14: 9658 | G14: 3039 | H14: 0 | I14: 0 | J14: 0 | K14: 0 | L14: 0
B15: Other Liabilities -
B16: Non controlling int | C16: 781 | D16: 1602 | E16: 937 | F16: 2364 | G16: 2587 | H16: 3270 | I16: 2655 | J16: 2093 | K16: 397 | L16: 183
B17: Trade Payables | C17: 18557 | D17: 18574 | E17: 20414 | F17: 21717 | G17: 21381 | H17: 25967 | I17: 36765 | J17: 37833 | K17: 30228 | L17: 29314
B18: Advance from Customers | C18: 456 | D18: 566 | E18: 616 | F18: 819 | G18: 869 | H18: 2399 | I18: 3253 | J18: 3394 | K18: 2771 | L18: 1655
B19: Other liability items | C19: 31371 | D19: 30871 | E19: 33738 | F19: 38131 | G19: 34408 | H19: 49533 | I19: 49744 | J19: 54101 | K19: 56799 | L19: 58335
B20: Total Liabilities | C20: 176884 | D20: 172447 | E20: 208722 | F20: 232773 | G20: 249149 | H20: 243909 | I20: 282422 | J20: 285396 | K20: 269312 | L20: 275459
B22: Fixed Assets - | C22: 72200 | D22: 92007 | E22: 96105 | F22: 124442 | G22: 134551 | H22: 135775 | I22: 133288 | J22: 146621 | K22: 148814 | L22: 150914
B23: Land | C23: 16499 | D23: 16545 | E23: 16955 | F23: 17126 | G23: 19853 | H23: 20656 | I23: 20770 | J23: 21701 | K23: 22067 | L23: 22299
B24: Building | C24: 11058 | D24: 11141 | E24: 12148 | F24: 21753 | G24: 25883 | H24: 26828 | I24: 27588 | J24: 28904 | K24: 30173 | L24: 31819
B25: Plant Machinery | C25: 73865 | D25: 93462 | E25: 104889 | F25: 127435 | G25: 141914 | H25: 155596 | I25: 152754 | J25: 163134 | K25: 175111 | L25: 186115
B26: Equipments | C26: 414 | D26: 543 | E26: 668 | F26: 739 | G26: 796 | H26: 0 | I26: 0 | J26: 0 | K26: 0 | L26: 0
B27: Furniture n fittings | C27: 0 | D27: 0 | E27: 0 | F27: 0 | G27: 19 | H27: 1047 | I27: 991 | J27: 1111 | K27: 1238 | L27: 1298
B28: Railway sidings | C28: 757 | D28: 1350 | E28: 1397 | F28: 1549 | G28: 1676 | H28: 1671 | I28: 1780 | J28: 1841 | K28: 1872 | L28: 1890
... B33: Accumulated Depreciation | C33: 41909 | D33: 39295 | E33: 49339 | F33: 52595 | G33: 66496 | H33: 82164 | I33: 88464 | J33: 98773 | K33: 110758 | L33: 122114
B34: Net Block | C34: =C32-C33 -> 72200 | D34: =D32-D33 -> 92007 | E34: =E32-E33 -> 96105 | F34: =F32-F33 -> 124442 | G34: =G32-G33 -> 134551 | H34: =H32-H33 -> 135775 | I34: =I32-I33 -> 133288 | J34: =J32-J33 -> 146622 | ... L34: =L32-L33 -> 150914
B36: CWIP | C36: 35996 | D36: 15784 | E36: 16614 | F36: 18641 | G36: 19497 | H36: 19007 | I36: 22046 | J36: 31213 | K36: 34356 | L36: 41622
B37: Investments | C37: 10714 | D37: 12457 | E37: 17899 | F37: 5738 | G37: 6285 | H37: 10682 | I37: 13140 | J37: 8410 | K37: 6258 | L37: 6194
B40: Other Assests-
B41: Inventories | C41: 20013 | D41: 24804 | E41: 28331 | F41: 31656 | G41: 31069 | H41: 33276 | I41: 48824 | J41: 54415 | K41: 49158 | L41: 44590
B42: Trade receivables | C42: 12066 | D42: 11587 | E42: 12416 | F42: 11811 | G42: 7885 | H42: 9540 | I42: 12246 | J42: 8257 | K42: 6264 | L42: 5260
B43: Cash Equivalents | C43: 6186 | D43: 4921 | E43: 7938 | F43: 3341 | G43: 8055 | H43: 5782 | I43: 15899 | J43: 13357 | K43: 8678 | L43: 11647
B44: Loans n Advances | C44: 107 | D44: 98 | E44: 219 | F44: -56 | G44: 195 | H44: -193 | I44: -158 | J44: -90 | K44: -56 | L44: -146
B45: Other asset items | C45: 19602 | D45: 10790 | E45: 29200 | F45: 37200 | G45: 41613 | H45: 30039 | I45: 37137 | J45: 23211 | K45: 15842 | L45: 15377
B46: Total Assets | C46: 176884 | D46: 172447 | E46: 208722 | F46: 232773 | G46: 249149 | H46: 243909 | I46: 282422 | J46: 285396 | K46: 269312 | L46: 275459
B50: Particulars | C50: 42430 | D50: 42795 | E50: 43160 | F50: 43525 | G50: 43891 | H50: 44256 | I50: 44621 | J50: 44986 | K50: 45352 | L50: 45717
B52: Cash from Operating Activity - | C52: 11455 | D52: 10824 | E52: 8023 | F52: 25336 | G52: 20169 | H52: 44327 | I52: 44381 | J52: 21683 | K52: 20301 | L52: 23512
B53: Profit from operations | C53: 6824 | D53: 17581 | E53: 20187 | F53: 27840 | G53: 18078 | H53: 28540 | I53: 65900 | J53: 30908 | K53: 22237 | L53: 23929
B54: Receivables | C54: 0 | D54: 0 | E54: 0 | F54: 0 | G54: 0 | H54: 0 | I54: 0 | J54: 0 | K54: 0 | L54: 0
B55: Inventory | C55: 5618 | D55: -8243 | E55: -1595 | F55: -1069 | G55: 1562 | H55: 46 | I55: -16917 | J55: -4031 | K55: 5566 | L55: 4776
B56: Payables | C56: 0 | D56: 0 | E56: 0 | F56: 0 | G56: 0 | H56: 0 | I56: 0 | J56: 0 | K56: 0 | L56: 0
... B82: Net Cash Flow | C82: -2068 | D82: -1245 | E82: 2933 | F82: -4513 | G82: 4462 | H82: -2200 | I82: 10075 | J82: -3477 | K82: -5049 | L82: 2524

Sheet Intrinsic growth
B2: TATA STEEL LTD
A4: # | B4: Calculation of ROIC | G4: 44256 | H4: 44621 | I4: 44986 | J4: 45352 | K4: 45717
B6: Current Assets
B7: ='IG raw Data'!B41 -> Inventories | G7: ='IG raw Data'!H41 -> 33276 | H7: ='IG raw Data'!I41 -> 48824 | I7: ='IG raw Data'!J41 -> 54415 | J7: ='IG raw Data'!K41 -> 49158 | K7: ='IG raw Data'!L41 -> 44590
B8: ='IG raw Data'!B42 -> Trade receivables | G8: ='IG raw Data'!H42 -> 9540 | H8: ='IG raw Data'!I42 -> 12246 | I8: ='IG raw Data'!J42 -> 8257 | J8: ='IG raw Data'!K42 -> 6264 | K8: ='IG raw Data'!L42 -> 5260
B9: ='IG raw Data'!B43 -> Cash Equivalents | G9: ='IG raw Data'!H43 -> 5782 | H9: ='IG raw Data'!I43 -> 15899 | I9: ='IG raw Data'!J43 -> 13357 | J9: ='IG raw Data'!K43 -> 8678 | K9: ='IG raw Data'!L43 -> 11647
B10: ='IG raw Data'!B44 -> Loans n Advances | G10: ='IG raw Data'!H44 -> -193 | H10: ='IG raw Data'!I44 -> -158 | I10: ='IG raw Data'!J44 -> -90 | J10: ='IG raw Data'!K44 -> -56 | K10: ='IG raw Data'!L44 -> -146
B11: ='IG raw Data'!B45 -> Other asset items | G11: ='IG raw Data'!H45 -> 30039 | H11: ='IG raw Data'!I45 -> 37137 | I11: ='IG raw Data'!J45 -> 23211 | J11: ='IG raw Data'!K45 -> 15842 | K11: ='IG raw Data'!L45 -> 15377
B12: Total Current Assets | G12: =SUM(G7:G11) -> 78444 | H12: =SUM(H7:H11) -> 113948 | I12: =SUM(I7:I11) -> 99150 | J12: =SUM(J7:J11) -> 79886 | K12: =SUM(K7:K11) -> 76728
B14: Current Liabilities
B15: Trade Payables | G15: ='IG raw Data'!H17 -> 25967 | H15: ='IG raw Data'!I17 -> 36765 | I15: ='IG raw Data'!J17 -> 37833 | J15: ='IG raw Data'!K17 -> 30228 | K15: ='IG raw Data'!L17 -> 29314
B16: Advance from Customers | G16: ='IG raw Data'!H18 -> 2399 | H16: ='IG raw Data'!I18 -> 3253 | I16: ='IG raw Data'!J18 -> 3394 | J16: ='IG raw Data'!K18 -> 2771 | K16: ='IG raw Data'!L18 -> 1655
B17: Other liability items | G17: ='IG raw Data'!H19 -> 49533 | H17: ='IG raw Data'!I19 -> 49744 | I17: ='IG raw Data'!J19 -> 54101 | J17: ='IG raw Data'!K19 -> 56799 | K17: ='IG raw Data'!L19 -> 58335
B18: Total Current Liabilities | G18: =SUM(G15:G17) -> 77899 | H18: =SUM(H15:H17) -> 89762 | I18: =SUM(I15:I17) -> 95328 | J18: =SUM(J15:J17) -> 89798 | K18: =SUM(K15:K17) -> 89304
A20: # | B20: Net Working Capital | G20: =G21 -> 545 | H20: =H21 -> 24186 | I20: =I21 -> 3822 | J20: =J21 -> -9912 | K20: =K21 -> -12576
G21: =G12-G18 -> 545 | H21: =H12-H18 -> 24186 | I21: =I12-I18 -> 3822 | J21: =J12-J18 -> -9912 | K21: =K12-K18 -> -12576
B22: Non- Current Assets
B23: ='IG raw Data'!B23 -> Land | G23: ='IG raw Data'!H23 -> 20656 | H23: ='IG raw Data'!I23 -> 20770 | I23: ='IG raw Data'!J23 -> 21701 | J23: ='IG raw Data'!K23 -> 22067 | K23: ='IG raw Data'!L23 -> 22299
B24: ='IG raw Data'!B24 -> Building | G24: ='IG raw Data'!H24 -> 26828 | H24: ='IG raw Data'!I24 -> 27588 | I24: ='IG raw Data'!J24 -> 28904 | J24: ='IG raw Data'!K24 -> 30173 | K24: ='IG raw Data'!L24 -> 31819
B25: ='IG raw Data'!B25 -> Plant Machinery | G25: ='IG raw Data'!H25 -> 155596 | H25: ='IG raw Data'!I25 -> 152754 | I25: ='IG raw Data'!J25 -> 163134 | J25: ='IG raw Data'!K25 -> 175111 | K25: ='IG raw Data'!L25 -> 186115
B26: ='IG raw Data'!B26 -> Equipments | G26: ='IG raw Data'!H26 -> 0 | H26: ='IG raw Data'!I26 -> 0 | I26: ='IG raw Data'!J26 -> 0 | J26: ='IG raw Data'!K26 -> 0 | K26: ='IG raw Data'!L26 -> 0
B27: ='IG raw Data'!B27 -> Furniture n fittings | G27: ='IG raw Data'!H27 -> 1047 | H27: ='IG raw Data'!I27 -> 991 | I27: ='IG raw Data'!J27 -> 1111 | J27: ='IG raw Data'!K27 -> 1238 | K27: ='IG raw Data'!L27 -> 1298
B28: ='IG raw Data'!B28 -> Railway sidings | G28: ='IG raw Data'!H28 -> 1671 | H28: ='IG raw Data'!I28 -> 1780 | I28: ='IG raw Data'!J28 -> 1841 | J28: ='IG raw Data'!K28 -> 1872 | K28: ='IG raw Data'!L28 -> 1890
B29: ='IG raw Data'!B29 -> Vehicles | G29: ='IG raw Data'!H29 -> 681 | H29: ='IG raw Data'!I29 -> 686 | I29: ='IG raw Data'!J29 -> 749 | J29: ='IG raw Data'!K29 -> 794 | K29: ='IG raw Data'!L29 -> 830
B30: ='IG raw Data'!B30 -> Intangible Assets | G30: ='IG raw Data'!H30 -> 6289 | H30: ='IG raw Data'!I30 -> 6229 | I30: ='IG raw Data'!J30 -> 7572 | J30: ='IG raw Data'!K30 -> 7772 | K30: ='IG raw Data'!L30 -> 7896
B31: ='IG raw Data'!B31 -> Other fixed assets | G31: ='IG raw Data'!H31 -> 5171 | H31: ='IG raw Data'!I31 -> 10953 | I31: ='IG raw Data'!J31 -> 20384 | J31: ='IG raw Data'!K31 -> 20546 | K31: ='IG raw Data'!L31 -> 20881
B33: Gross Block | G33: ='IG raw Data'!H32 -> 217939 | H33: ='IG raw Data'!I32 -> 221752 | I33: ='IG raw Data'!J32 -> 245395 | J33: ='IG raw Data'!K32 -> 259572 | K33: ='IG raw Data'!L32 -> 273028
B34: Accumulated Depreciation | G34: ='IG raw Data'!H33 -> 82164 | H34: ='IG raw Data'!I33 -> 88464 | I34: ='IG raw Data'!J33 -> 98773 | J34: ='IG raw Data'!K33 -> 110758 | K34: ='IG raw Data'!L33 -> 122114
A36: # | B36: Net Non- Current Assets | G36: =SUM(G33:G34) -> 300103 | H36: =SUM(H33:H34) -> 310216 | I36: =SUM(I33:I34) -> 344168 | J36: =SUM(J33:J34) -> 370330 | K36: =SUM(K33:K34) -> 395142
A38: # | B38: Invested Capital | G38: =G36+G20 -> 300648 | H38: =H36+H20 -> 334402 | I38: =I36+I20 -> 347990 | J38: =J36+J20 -> 360418 | K38: =K36+K20 -> 382566
B39: EBIT | G39: ='HISTORICAL(FS)'!H19-'HISTORICAL(FS)'!H25 -> 21270.62 | H39: ='HISTORICAL(FS)'!I19-'HISTORICAL(FS)'!I25 -> 54389.08 | I39: ='HISTORICAL(FS)'!J19-'HISTORICAL(FS)'!J25 -> 22964.96 | J39: ='HISTORICAL(FS)'!K19-'HISTORICAL(FS)'!K25 -> 12365.76 | K39: ='HISTORICAL(FS)'!L19-'HISTORICAL(FS)'!L25 -> 14877.12
A41: # | B41: ROIC | G41: =G39/G38 -> 0.070749248 | H41: =H39/H38 -> 0.1626458 | I41: =I39/I38 -> 0.065993161 | J41: =J39/J38 -> 0.034309496 | K41: =K39/K38 -> 0.038887721
A43: # | B43: Calculation of Reinvestment Rate | G43: 44256 | H43: 44621 | I43: 44986 | J43: 45352 | K43: 45717
B45: Net Capex | G45: =-SUM('IG raw Data'!H62:H63) -> 6534 | H45: =-SUM('IG raw Data'!I62:I63) -> 9953 | I45: =-SUM('IG raw Data'!J62:J63) -> 13814 | J45: =-SUM('IG raw Data'!K62:K63) -> 17732 | K45: =-SUM('IG raw Data'!L62:L63) -> 14407
B46: Change in Working Capital | H46: =H20-G20 -> 23641 | I46: =I20-H20 -> -20364 | J46: =J20-I20 -> -13734 | K46: =K20-J20 -> -2664
B48: EBIT | G48: =G39 -> 21270.62 | H48: =H39 -> 54389.08 | I48: =I39 -> 22964.96 | J48: =J39 -> 12365.76 | K48: =K39 -> 14877.12
B49: Marginal Tax Rate | G49: 0.25 | H49: 0.25 | I49: 0.25 | J49: 0.25 | K49: 0.25
B50: EBIT(1-T) | G50: =G48*(1-G49) -> 15952.965 | H50: =H48*(1-H49) -> 40791.81 | I50: =I48*(1-I49) -> 17223.72 | J50: =J48*(1-J49) -> 9274.32 | K50: =K48*(1-K49) -> 11157.84
B52: Reinvestment Amount | H52: =SUM(H45:H46) -> 33594 | I52: =SUM(I45:I46) -> -6550 | J52: =SUM(J45:J46) -> 3998 | K52: =SUM(K45:K46) -> 11743
B54: Reinvestment Rate | H54: =H52/H50 -> 0.82354767 | I54: =I52/I50 -> -0.38028951 | J54: =J52/J50 -> 0.43108282 | K54: =K52/K50 -> 1.0524438
J56: 4 Year Average | K56: =AVERAGE(H54:K54) -> 0.48169621
J57: 4 Year Median | K57: =MEDIAN(H54:K54) -> 0.62731524
A59: # | B59: Calculation of Growth Rate | G59: 44256 | H59: 44621 | I59: 44986 | J59: 45352 | K59: 45717
B61: Reinvestment Rate | H61: =H54 -> 0.82354767 | I61: =I54 -> -0.38028951 | J61: =J54 -> 0.43108282 | K61: =K54 -> 1.0524438
B62: ROIC | H62: =H41 -> 0.1626458 | I62: =I41 -> 0.065993161 | J62: =J41 -> 0.034309496 | K62: =K41 -> 0.038887721
B64: Intrinsic Growth | H64: =H61*H62 -> 0.13394657 | I64: =I61*I62 -> -0.025096507 | J64: =J61*J62 -> 0.014790234 | K64: =K61*K62 -> 0.040927143
J66: 4 Year Average | K66: =AVERAGE(H64:K64) -> 0.041141859
J67: 4 Year Median | K67: =MEDIAN(H64:K64) -> 0.027858689

Sheet PV of FCFF
B2: TATA STEEL LTD
B4: Calculation of PV of FCFF | F4: Mar - 25A | G4: Mar - 26F | H4: Mar -27F | I4: Mar -28F | J4: Mar -29F | K4: Mar -30F
B6: EBIT | F6: ='Intrinsic growth'!K39 -> 14877.12 | G6: =F6*(1+$D$16) -> 15583.783 | H6: =G6*(1+$D$16) -> 16324.013 | I6: =H6*(1+$D$16) -> 17099.404 | J6: =I6*(1+$D$16) -> 17911.625 | K6: =J6*(1+$D$16) -> 18762.427
B7: Tax Rate | F7: 0.25 | G7: =F7 -> 0.25 | H7: =G7 -> 0.25 | I7: =H7 -> 0.25 | J7: =I7 -> 0.25 | K7: =J7 -> 0.25
B8: EBIT(1-T) | F8: =F6*(1-F7) -> 11157.84 | G8: =G6*(1-G7) -> 11687.837 | H8: =H6*(1-H7) -> 12243.01 | I8: =I6*(1-I7) -> 12824.553 | J8: =J6*(1-J7) -> 13433.719 | K8: =K6*(1-K7) -> 14071.821
B9: Less: Reinvestment Rate | F9: ='Intrinsic growth'!K57 -> 0.62731524 | G9: =F9+(($K$9-$F$9)/4) -> 0.63616143 | H9: =G9+(($K$9-$F$9)/4) -> 0.64500762 | I9: =H9+(($K$9-$F$9)/4) -> 0.65385381 | J9: =I9+(($K$9-$F$9)/4) -> 0.6627 | K9: 0.6627
B10: Free Cash Flow to Firm (FCFF) | F10: =F8*(1-F9) -> 4158.3569 | G10: =G8*(1-G9) -> 4252.486 | H10: =H8*(1-H9) -> 4346.1751 | I10: =I8*(1-I9) -> 4439.17 | J10: =J8*(1-J9) -> 4531.1934 | K10: =K8*(1-K9) -> 4746.4251
B11: Mid Year Convention | G11: 0.5 | H11: =G11+1 -> 1.5 | I11: =H11+1 -> 2.5 | J11: =I11+1 -> 3.5 | K11: =J11+1 -> 4.5
B12: Discounting Factor | G12: =1/(1+$D$18)^G11 -> 0.93490801 | H12: =1/(1+$D$18)^H11 -> 0.81715915 | I12: =1/(1+$D$18)^I11 -> 0.7142404 | J12: =1/(1+$D$18)^J11 -> 0.62428396 | K12: =1/(1+$D$18)^K11 -> 0.54565727
B14: PV of FCFF | G14: =G10*G12 -> 3975.6833 | H14: =H10*H12 -> 3551.5168 | I14: =I10*I12 -> 3170.6346 | J14: =J10*J12 -> 2828.7514 | K14: =K10*K12 -> 2589.9213
B16: Expected Growth | D16: 0.0475
B17: Terminal Growth | D17: 0.065
B18: WACC | D18: ='DCF Modelling(WACC)'!L49 -> 0.14409539
B21: Calculation of Terminal Value
B23: FCFF(n+1) | D23: =K10*(1+D16) -> 4971.8803
B24: WACC | D24: =D18 -> 0.14409539
B25: Terminal Growth Rate | D25: =D17 -> 0.065 | G25: Sensitivity Analysis - Value of Operating Activities | N25: Equity Analysis - Equity value per Share
B27: Terminal Value | D27: =D23/(D24-D25) -> 62859.295
I28: WACC | P28: WACC
B29: Calculation of Equity Value per Share
G30: =D33 -> 50416.139 | H30: 0.1452 | I30: 0.1441 | J30: 0.1675 | K30: 0.1832 | N30: =D40 -> 21.546876 | O30: 0.1452 | P30: 0.1441 | Q30: 0.1675 | R30: 0.1832
B31: PV of FCFF | D31: =SUM(G14:K14) -> 16116.507 | F31: Terminal | G31: 0.055 | H31: 46193.476 | I31: 46564.797 | J31: 40231.553 | K31: 37278.306 | M31: Terminal | N31: 0.055 | O31: 24.929113 | P31: 24.631696 | Q31: 29.704452 | R31: 32.069923
B32: PV of Terminal Value | D32: =D27*K12 -> 34299.631 | F32: Growth | G32: 0.065 | H32: 49943.722 | I32: 50414.138 | J32: 42584.24 | K32: 39068.644 | M32: Growth | N32: 0.065 | O32: 21.925269 | P32: 21.548478 | Q32: 27.820014 | R32: 30.63591
B33: Value of Operating Assets | D33: =SUM(D31:D32) -> 50416.139 | F33: rate | G33: 0.07 | H33: 52192.872 | I33: 52728.418 | J33: 43941.56 | K33: 40082.431 | M33: rate | N33: 0.07 | O33: 20.123761 | P33: 19.694802 | Q33: 26.732837 | R33: 29.823894
G34: 0.075 | H34: 54762.413 | I34: 55377.616 | J34: 45445.617 | K34: 41189.914 | N34: 0.075 | O34: 18.065628 | P34: 17.572867 | Q34: 25.528129 | R34: 28.936831
B35: Add: Cash | C35: ='data sheet'!K68 -> 11646.98 | D35: ='data sheet'!K68 -> 11646.98
B36: Less: Debt | C36: =SUM('IG raw Data'!L10:L11) -> 88964 | D36: 88964
B37: Value of Equity | C37: =D33+C35-C36 -> -26900.881 | D37: =D33+D35-D36 -> -26900.881
B38: No of Shares | D38: ='data sheet'!B6 -> 1248.4818
B40: Equity Value per Share | D40: =-D37/D38 -> 21.546876
B42: Share price | D42: 197
B43: Discount/Premium | D43: =D42/D40-1 -> 8.1428569

Sheet Football field analysis
B2: TATA STEEL LTD
B4: Football Field Analysis Table - TATA MOTORS LTD
L7: Football Field Analysis - Data
N9: Openlow | O9: Low | P9: Openhigh | Q9: High
L10: Comps | N10: =O10 -> 125.2 | O10: 125.2 | P10: =Q10 -> 211.6 | Q10: 211.6
L11: DCF Bear | N11: =O11 -> 121.2 | O11: 121.2 | P11: =Q11 -> 153.5 | Q11: 153.5
L12: DCF Base | N12: =O12 -> 121.2 | O12: 121.2 | P12: =Q12 -> 219.4 | Q12: 219.4
L13: DCF Bull | N13: =O13 -> 210.7 | O13: 210.7 | P13: =Q13 -> 303.8 | Q13: 303.8
L14: 52W/L | N14: =O14 -> 125.3 | O14: 125.3 | P14: =Q14 -> 216.45 | Q14: 216.45

Sheet RV Data
B3: Peer comps data for Relative Valuation
B9: . | C9: Name | D9: CMP Rs. | E9: No. Eq. Shares | F9: Market cap. | G9: Debt | H9: Net Debt | I9: Cash End | J9: EV(new) | K9: Sales | L9: NP | M9: Tax | N9: Interest | O9: Dep | P9: Mar Cap | Q9: EBITDA | R9: E.margin
B10: 1 | C10: JSW Steel | D10: 1169.6 | E10: 244.55 | F10: =E10*D10 -> 286025.68 | G10: 101107 | H10: =G10-I10 -> 87822 | I10: 13285 | J10: =F10+G10-I10 -> 373847.68 | K10: 179109 | L10: 7766 | M10: 837 | N10: 9028 | O10: 9950 | P10: 285767.61 | Q10: =K10+L10+M10+N10+O10 -> 206690 | R10: =Q10/K10*100% -> 1.15399
B11: 2 | C11: Tata Steel | D11: 196.77 | E11: 1248.35 | F11: =E11*D11 -> 245637.83 | G11: 95643.13 | H11: =G11-I11 -> 83996.15 | I11: 11646.98 | J11: =F11+G11-I11 -> 329633.98 | K11: 225087.92 | L11: 9121.7 | M11: 4236.31 | N11: 7163.43 | O11: 11406.08 | P11: 245586.8 | Q11: =K11+L11+M11+N11+O11 -> 257015.44 | R11: =Q11/K11*100% -> 1.1418447
B12: 3 | C12: Jindal Steel | D12: 1186.5 | E12: 102.01 | F12: =E12*D12 -> 121034.87 | G12: 19155.98 | H12: =G12-I12 -> 14975.93 | I12: 4180.05 | J12: =F12+G12-I12 -> 136010.8 | K12: 50190.12 | L12: 2016.04 | M12: 1394.77 | N12: 1415.88 | O12: 3000.28 | P12: 121044.09 | Q12: =K12+L12+M12+N12+O12 -> 58017.09 | R12: =Q12/K12*100% -> 1.1559464
B13: 4 | C13: S A I L | D13: 155.52 | E13: 413.05 | F13: =E13*D13 -> 64237.536 | G13: 33663.18 | H13: =G13-I13 -> 32696.3 | I13: 966.88 | J13: =F13+G13-I13 -> 96933.836 | K13: 109313.49 | L13: 2788.31 | M13: 872.61 | N13: 2290.55 | O13: 5934.33 | P13: 64406.81 | Q13: =K13+L13+M13+N13+O13 -> 121199.29 | R13: =Q13/K13*100% -> 1.1087313
B14: 5 | C14: Jindal Stain. | D14: 721.95 | E14: 82.44 | F14: =E14*D14 -> 59517.558 | G14: 6861.97 | H14: =G14-I14 -> 4592.1 | I14: 2269.87 | J14: =F14+G14-I14 -> 64109.658 | K14: 41815.79 | L14: 2940.32 | M14: 918.18 | N14: 568.94 | O14: 1023.87 | P14: 59493.76 | Q14: =K14+L14+M14+N14+O14 -> 47267.1 | R14: =Q14/K14*100% -> 1.1303649
B15: 6 | C15: Sarda Energy | D15: 508.75 | E15: 35.24 | F15: =E15*D15 -> 17928.35 | G15: 2680.55 | H15: =G15-I15 -> 2072.32 | I15: 608.23 | J15: =F15+G15-I15 -> 20000.67 | K15: 5675.72 | L15: 1054.69 | M15: 382.71 | N15: 260.96 | O15: 339.14 | P15: 17916.85 | Q15: =K15+L15+M15+N15+O15 -> 7713.22 | R15: =Q15/K15*100% -> 1.3589853
B16: 7 | C16: NMDC Steel | D16: 36.7 | E16: 293.06 | F16: =E16*D16 -> 10755.302 | G16: 5309.93 | H16: =G16-I16 -> 4402.29 | I16: 907.64 | J16: =F16+G16-I16 -> 15157.592 | K16: 12601.06 | L16: -806.58 | M16: -268.05 | N16: 562.72 | O16: 1012.92 | P16: 10746.37 | Q16: =K16+L16+M16+N16+O16 -> 13102.07 | R16: =Q16/K16*100% -> 1.0397594

Sheet Relative valuation
B2: TATA STEEL LTD
B4: Amount in crores
B6: Comparable Company Valuation
D8: Market Data | J8: Financials | M8: Valuation
D9: Share | E9: Shares | H9: Enterprise
B10: Company | C10: Ticker | D10: Price | E10: Outstanding | F10: Equity Value | G10: Net Debt | H10: Value | J10: Revenue | K10: EBITDA | L10: Net Income | N10: EV/Revenue | O10: EV/EBITDA | P10: P/E
B12: JSW Steel | D12: ='RV Data'!D10 -> 1169.6 | E12: ='RV Data'!E10 -> 244.55 | F12: =E12*D12 -> 286025.68 | G12: ='RV Data'!H10 -> 87822 | H12: =F12+G12 -> 373847.68 | J12: ='RV Data'!K10 -> 179109 | K12: ='RV Data'!Q10 -> 206690 | L12: ='RV Data'!L10 -> 7766 | N12: =$H12/J12 -> 2.0872635 | O12: =$H12/K12 -> 1.8087362 | P12: =F12/L12 -> 36.830502
B13: Tata Steel | D13: ='RV Data'!D11 -> 196.77 | E13: ='RV Data'!E11 -> 1248.35 | F13: =E13*D13 -> 245637.83 | G13: ='RV Data'!H11 -> 83996.15 | H13: =F13+G13 -> 329633.98 | J13: ='RV Data'!K11 -> 225087.92 | K13: ='RV Data'!Q11 -> 257015.44 | L13: ='RV Data'!L11 -> 9121.7 | N13: =$H13/J13 -> 1.4644677 | O13: =$H13/K13 -> 1.2825454 | P13: =F13/L13 -> 26.928953
B14: Jindal Steel | D14: ='RV Data'!D12 -> 1186.5 | E14: ='RV Data'!E12 -> 102.01 | F14: =E14*D14 -> 121034.87 | G14: ='RV Data'!H12 -> 14975.93 | H14: =F14+G14 -> 136010.8 | J14: ='RV Data'!K12 -> 50190.12 | K14: ='RV Data'!Q12 -> 58017.09 | L14: ='RV Data'!L12 -> 2016.04 | N14: =$H14/J14 -> 2.7099117 | O14: =$H14/K14 -> 2.3443229 | P14: =F14/L14 -> 60.035944
B15: S A I L | D15: ='RV Data'!D13 -> 155.52 | E15: ='RV Data'!E13 -> 413.05 | F15: =E15*D15 -> 64237.536 | G15: ='RV Data'!H13 -> 32696.3 | H15: =F15+G15 -> 96933.836 | J15: ='RV Data'!K13 -> 109313.49 | K15: ='RV Data'!Q13 -> 121199.29 | L15: ='RV Data'!L13 -> 2788.31 | N15: =$H15/J15 -> 0.8867509 | O15: =$H15/K15 -> 0.79978881 | P15: =F15/L15 -> 23.038161
B16: Jindal Stain. | D16: ='RV Data'!D14 -> 721.95 | E16: ='RV Data'!E14 -> 82.44 | F16: =E16*D16 -> 59517.558 | G16: ='RV Data'!H14 -> 4592.1 | H16: =F16+G16 -> 64109.658 | J16: ='RV Data'!K14 -> 41815.79 | K16: ='RV Data'!Q14 -> 47267.1 | L16: ='RV Data'!L14 -> 2940.32 | N16: =$H16/J16 -> 1.5331447 | O16: =$H16/K16 -> 1.3563273 | P16: =F16/L16 -> 20.241864
B17: Sarda Energy | D17: ='RV Data'!D15 -> 508.75 | E17: ='RV Data'!E15 -> 35.24 | F17: =E17*D17 -> 17928.35 | G17: ='RV Data'!H15 -> 2072.32 | H17: =F17+G17 -> 20000.67 | J17: ='RV Data'!K15 -> 5675.72 | K17: ='RV Data'!Q15 -> 7713.22 | L17: ='RV Data'!L15 -> 1054.69 | N17: =$H17/J17 -> 3.5239001 | O17: =$H17/K17 -> 2.5930377 | P17: =F17/L17 -> 16.998692
B18: NMDC Steel | D18: ='RV Data'!D16 -> 36.7 | E18: ='RV Data'!E16 -> 293.06 | F18: =E18*D18 -> 10755.302 | G18: ='RV Data'!H16 -> 4402.29 | H18: =F18+G18 -> 15157.592 | J18: ='RV Data'!K16 -> 12601.06 | K18: ='RV Data'!Q16 -> 13102.07 | L18: ='RV Data'!L16 -> -806.58 | N18: =$H18/J18 -> 1.2028823 | O18: =$H18/K18 -> 1.1568853 | P18: =F18/L18 -> -13.334452
B20: High | N20: =MAX(N12:N18) -> 3.5239001 | O20: =MAX(O12:O18) -> 2.5930377 | P20: =MAX(P12:P18) -> 60.035944
B21: 75th Percentile | N21: =QUARTILE(N12:N18,3) -> 2.3985876 | O21: =QUARTILE(O12:O18,3) -> 2.0765296 | P21: =QUARTILE(P12:P18,3) -> 31.879728
B22: Average | N22: =AVERAGE(N12:N18) -> 1.9154744 | O22: =AVERAGE(O12:O18) -> 1.6202348 | P22: =AVERAGE(P12:P18) -> 24.391381
B23: Median | N23: =MEDIAN(N12:N18) -> 1.5331447 | O23: =MEDIAN(O12:O18) -> 1.3563273 | P23: =MEDIAN(P12:P18) -> 23.038161
B24: 25th Percentile | N24: =MEDIAN(N13:N19) -> 1.4988062 | O24: =MEDIAN(O13:O19) -> 1.3194364 | P24: =MEDIAN(P13:P19) -> 21.640013
B25: Low | N25: =MEDIAN(N14:N20) -> 2.1215282 | O25: =MEDIAN(O14:O20) -> 1.8503251 | P25: =MEDIAN(P14:P20) -> 21.640013
B27: Cipla Comparable Valuation | N27: EV/Revenue | O27: EV/EBITDA | P27: P/E
B29: Implied Enterprise Value | N29: =N23*J13 -> 345092.36 | O29: =N23*O13 -> 1.9663278 | P29: =P31+P30 -> 294143.35
B30: Net Debt | N30: =$G$13 -> 83996.15 | O30: =$G$13 -> 83996.15 | P30: =$G$13 -> 83996.15
B31: Implied Market Value | N31: =N29-N30 -> 261096.21 | O31: =O29-O30 -> -83994.184 | P31: =P23*L13 -> 210147.2
B32: Shares Outstanding | N32: =$E$13 -> 1248.35 | O32: =$E$13 -> 1248.35 | P32: =$E$13 -> 1248.35
B34: Implied Value per Share | N34: =N31/N32 -> 209.15305 | O34: =O31/O32 -> -67.284162 | P34: =P31/P32 -> 168.33997
B36: Source: Screener.in
N37: =IF(N34>$D$13, "Undervalued","Overvalued") -> Undervalued | O37: =IF(O34>$D$13, "Undervalued","Overvalued") -> Overvalued | P37: =IF(P34>$D$13, "Undervalued","Overvalued") -> Overvalued

Sheet data sheet
A1: COMPANY NAME | B1: TATA STEEL LTD | E1: =IF(B2<>B3, "A NEW VERSION OF THE WORKSHEET IS AVAILABLE", "")
A2: LATEST VERSION | B2: 2.1 | E2: PLEASE DO NOT MAKE ANY CHANGES TO THIS SHEET
A3: CURRENT VERSION | B3: 2.1
E4: TATA STEEL LTD
A5: META
A6: Number of shares | B6: =IF(B9>0, B9/B8, 0) -> 1248.4818
A7: Face Value | B7: 1
A8: Current Price | B8: 183.51
A9: Market Capitalization | B9: 229108.89
A15: PROFIT & LOSS
A16: Report Date | B16: 42460 | C16: 42825 | D16: 43190 | E16: 43555 | F16: 43921 | G16: 44286 | H16: 44651 | I16: 45016 | J16: 45382 | K16: 45747
A17: Sales | B17: 101964.72 | C17: 112299.42 | D17: 123249.07 | E17: 157668.99 | F17: 139816.65 | G17: 156477.4 | H17: 243959.17 | I17: 243352.69 | J17: 229170.78 | K17: 218542.51
A18: Raw Material Cost | B18: 38696.27 | C18: 43843.03 | D18: 46137.01 | E18: 60877.05 | F18: 58039.99 | G18: 55100.81 | H18: 91076.61 | I18: 116597.19 | J18: 97506.39 | K18: 95097.3
A19: Change in Inventory | B19: -1925.19 | C19: 4538.13 | D19: -99.31 | E19: 96.71 | F19: 565.24 | G19: -1516.77 | H19: 7597.87 | I19: 3358.89 | J19: -4409.35 | K19: 96.65
A20: Power and Fuel | B20: 4993.89 | C20: 5220.83 | D20: 4440.43 | E20: 5316.56 | F20: 5319.92 | G20: 5708.42 | H20: 8028.29 | I20: 9526.91 | J20: 16612.61 | K20: 13124.85
A21: Other Mfr. Exp | B21: 16034.28 | C21: 15799.14 | D21: 16955.79 | E21: 20734.28 | F21: 21232.69 | G21: 20744.93 | H21: 28834.06 | I21: 33144.83 | J21: 40116.91 | K21: 38700.5
A22: Employee Cost | B22: 17587.63 | C22: 17252.22 | D22: 17077.51 | E22: 18758.87 | F22: 18533.58 | G22: 19908.81 | H22: 23264.1 | I22: 22419.32 | J22: 24509.58 | K22: 24888.99
A23: Selling and admin | B23: 12908.42 | C23: 13772.32 | D23: 14423.87 | E23: 16917.14 | F23: 15599.07 | G23: 17509.77 | H23: 27445.67 | I23: 25519.92 | J23: 14453.57 | K23: 12137.26
A24: Other Expenses | B24: 10444.28 | C24: 7806.38 | D24: 2681.96 | E24: 5843.58 | F24: 4193.58 | G24: 5483.63 | H24: 9418.36 | I24: 7203.25 | J24: 9314.45 | K24: 9391.81
A25: Other Income | B25: 10345.87 | C25: -3789.11 | D25: 10898.41 | E25: 1524.31 | F25: -2883.63 | G25: 179.78 | H25: 1299.99 | I25: 1568.86 | J25: -6005.23 | K25: 876.7
A26: Depreciation | B26: 5306.35 | C26: 5672.88 | D26: 5741.7 | E26: 7341.83 | F26: 8440.73 | G26: 9233.64 | H26: 9100.87 | I26: 9335.2 | J26: 9882.16 | K26: 10421.33
A27: Interest | B27: 4221.41 | C27: 5072.2 | D27: 5454.74 | E27: 7660.1 | F27: 7533.46 | G27: 7606.71 | H27: 5462.2 | I27: 6298.7 | J27: 7507.57 | K27: 7340.95
... A31: Dividend Amount | B31: 776.19 | C31: 970.24 | D31: 1144.95 | E31: 1488.42 | F31: 1144.95 | G31: 2994.02 | H31: 6228.17 | I31: 4396.46 | J31: 4490.78 | K31: 4490.78
A32: EBITDA | B32: =B26+B27+B29+B30 -> 9834.94 | C32: =C26+C27+C29+C30 -> 9282.29 | D32: =D26+D27+D29+D30 -> 28023.1 | E32: =E26+E27+E29+E30 -> 31938.69 | F32: =F26+F27+F29+F30 -> 14962.32 | G32: =G26+G27+G29+G30 -> 29984.47 | H32: =H26+H27+H29+H30 -> 63194.55 | I32: =I26+I27+I29+I30 -> 34554.07 | ... K32: =K26+K27+K29+K30 -> 26421.88
A36: Market capitalisation | B36: =G93/G90 -> 14.738145
A39: Quarters
A40: Report Date | B40: 45199 | C40: 45291 | D40: 45382 | E40: 45473 | F40: 45565 | G40: 45657 | H40: 45747 | I40: 45838 | J40: 45930 | K40: 46022
A41: Sales | B41: 55681.93 | C41: 55311.88 | D41: 58687.31 | E41: 54771.39 | F41: 53904.71 | G41: 53648.3 | H41: 56218.11 | I41: 53178.12 | J41: 58689.29 | K41: 57002.4
A42: Expenses | B42: 51414.11 | C42: 49048.31 | D42: 52086.68 | E42: 48076.92 | F42: 47788.92 | G42: 47744.81 | H42: 49658.89 | I42: 45750.58 | J42: 49792.75 | K42: 48802.7
A43: Other Income | B43: -6567.77 | C43: -32.84 | D43: -381.56 | E43: -5.51 | F43: 616.68 | G43: 141.82 | H43: 149.19 | I43: 236.27 | J43: -6.11 | K43: 465.17
A44: Depreciation | B44: 2479.85 | C44: 2422.04 | D44: 2567.95 | E44: 2535.43 | F44: 2596.74 | G44: 2569.19 | H44: 2719.97 | I44: 2744.3 | J44: 2893 | K44: 3048.81
A45: Interest | B45: 1959.39 | C45: 1880.78 | D45: 1842.25 | E45: 1776.71 | F45: 1971.4 | G45: 1804.09 | H45: 1788.75 | I45: 1852.43 | J45: 1774.96 | K45: 1747.29
A46: Profit before tax | B46: -6739.19 | C46: 1927.91 | D46: 1808.87 | E46: 2376.82 | F46: 2164.33 | G46: 1672.03 | H46: 2199.69 | I46: 3067.08 | J46: 4222.47 | K46: 3868.77
A47: Tax | B47: -228.03 | C47: 1405.77 | D47: 1254.31 | E47: 1458.25 | F47: 1405.49 | G47: 1376.54 | H47: 998.81 | I47: 1059.72 | J47: 1039.38 | K47: 1138.4
A48: Net profit | B48: -6196.24 | C48: 513.37 | D48: 611.48 | E48: 959.61 | F48: 833.45 | G48: 326.64 | H48: 1300.81 | I48: 2077.68 | J48: 3101.75 | K48: 2688.7
A49: Operating Profit | B49: 4267.82 | C49: 6263.57 | D49: 6600.63 | E49: 6694.47 | F49: 6115.79 | G49: 5903.49 | H49: 6559.22 | I49: 7427.54 | J49: 8896.54 | K49: 8199.7
A51: EBITDA | B51: =B48+B47+B45+B44 -> -1985.03 | C51: =C48+C47+C45+C44 -> 6221.96 | D51: =D48+D47+D45+D44 -> 6275.99 | E51: =E48+E47+E45+E44 -> 6730 | F51: =F48+F47+F45+F44 -> 6807.08 | G51: =G48+G47+G45+G44 -> 6076.46 | H51: =H48+H47+H45+H44 -> 6808.34 | I51: =I48+I47+I45+I44 -> 7734.13 | ... K51: =K48+K47+K45+K44 -> 8623.2
A54: BALANCE SHEET
A55: Report Date | B55: 42460 | C55: 42825 | D55: 43190 | E55: 43555 | F55: 43921 | G55: 44286 | H55: 44651 | I55: 45016 | J55: 45382 | K55: 45747
A56: Equity Share Capital | B56: 970.24 | C56: 970.24 | D56: 1144.95 | E56: 1144.94 | F56: 1144.95 | G56: 1197.61 | H56: 1221.21 | I56: 1221.24 | J56: 1247.44 | K56: 1247.44
A57: Reserves | B57: 42762.31 | C57: 36849.08 | D57: 59725.67 | E57: 67780.14 | F57: 72431.35 | G57: 73041.16 | H57: 113221.83 | I57: 101860.86 | J57: 90788.32 | K57: 89922.19
A58: Borrowings | B58: 81986.93 | C58: 83014.49 | D58: 92147.05 | E58: 100816.22 | F58: 116328.2 | G58: 88501.41 | H58: 75561.35 | I58: 84893.05 | J58: 87082.12 | K58: 94801.05
A59: Other Liabilities | B59: 51164.51 | C59: 51613.56 | D59: 55704.47 | E59: 63032.14 | F59: 59244.62 | G59: 81169.01 | H59: 92417.28 | I59: 97420.63 | J59: 90194.54 | K59: 89487.9
A60: Total | B60: 176883.99 | C60: 172447.37 | D60: 208722.14 | E60: 232773.44 | F60: 249149.12 | G60: 243909.19 | H60: 282421.67 | I60: 285395.78 | J60: 269312.42 | K60: 275458.58
A61: Net Block | B61: 72199.76 | C61: 92006.55 | D61: 96104.89 | E61: 124441.91 | F61: 134550.66 | G61: 135775.18 | H61: 133287.83 | I61: 146621.46 | J61: 148814.38 | K61: 150914.06
A62: Capital Work in Progress | B62: 35996.09 | C62: 15784.13 | D62: 16614.41 | E62: 18641.21 | F62: 19496.83 | G62: 19007.4 | H62: 22045.55 | I62: 31213.02 | J62: 34355.53 | K62: 41622.35
A63: Investments | B63: 10713.71 | C63: 12457.12 | D63: 17899.47 | E63: 5738.17 | F63: 6285.18 | G63: 10681.93 | H63: 13139.85 | I63: 8410.31 | J63: 6257.57 | K63: 6194.11
A64: Other Assets | B64: 57974.43 | C64: 52199.57 | D64: 78103.37 | E64: 83952.15 | F64: 88816.45 | G64: 78444.68 | H64: 113948.44 | I64: 99150.99 | J64: 79884.94 | K64: 76728.06
A65: Total | B65: 176883.99 | C65: 172447.37 | D65: 208722.14 | E65: 232773.44 | F65: 249149.12 | G65: 243909.19 | H65: 282421.67 | I65: 285395.78 | J65: 269312.42 | K65: 275458.58
A66: Receivables | B66: 12066.22 | C66: 11586.82 | D66: 12415.52 | E66: 11811 | F66: 7884.91 | G66: 9539.84 | H66: 12246.43 | I66: 8257.24 | J66: 6263.53 | K66: 5260.06
... A69: No. of Equity Shares | B69: 970436562 | C69: 970436562 | D69: 1203340563 | E69: 1203331928 | F69: 1203332459 | G69: 1203334622 | H69: 1221566453 | I69: 12212353070 | J69: 12474347611 | K69: 12474347611
A70: New Bonus Shares
A71: Face value | B71: 10 | C71: 10 | D71: 10 | E71: 10 | F71: 10 | G71: 10 | H71: 10 | I71: 1 | J71: 1 | K71: 1
A73: Other Assets | B73: =B64-SUM(B66:B68) -> 19708.54 | C73: =C64-SUM(C66:C68) -> 10887.88 | D73: =D64-SUM(D66:D68) -> 29418.96 | E73: =E64-SUM(E66:E68) -> 37143.68 | F73: =F64-SUM(F66:F68) -> 41808.1 | G73: =G64-SUM(G66:G68) -> 29846.28 | H73: =H64-SUM(H66:H68) -> 36978.69 | I73: =I64-SUM(I66:I68) -> 23121.16 | ... K73: =K64-SUM(K66:K68) -> 15231.08
A74: total assets | B74: =B60 -> 176883.99 | C74: =C60 -> 172447.37 | D74: =D60 -> 208722.14 | E74: =E60 -> 232773.44 | F74: =F60 -> 249149.12 | G74: =G60 -> 243909.19 | H74: =H60 -> 282421.67 | I74: =I60 -> 285395.78 | ... K74: =K60 -> 275458.58
A80: CASH FLOW:
A81: Report Date | B81: 42460 | C81: 42825 | D81: 43190 | E81: 43555 | F81: 43921 | G81: 44286 | H81: 44651 | I81: 45016 | J81: 45382 | K81: 45747
A82: Cash from Operating Activity | B82: 11455.35 | C82: 10824.36 | D82: 8023.39 | E82: 25335.95 | F82: 20168.72 | G82: 44326.68 | H82: 44380.99 | I82: 21683.08 | J82: 20300.67 | K82: 23511.81
A83: Cash from Investing Activity | B83: -8794.31 | C83: -9489.65 | D83: -11730.31 | E83: -29176.45 | F83: -14012.06 | G83: -9437.27 | H83: -10905.02 | I83: -18179.45 | J83: -14252.74 | K83: -13985.25
A84: Cash from Financing Activity | B84: -4729.12 | C84: -2579.36 | D84: 6639.94 | E84: -672.7 | F84: -1694.62 | G84: -37089.67 | H84: -23401.09 | I84: -6980.69 | J84: -11096.99 | K84: -7002.44
A85: Net Cash Flow | B85: -2068.08 | C85: -1244.65 | D85: 2933.02 | E85: -4513.2 | F85: 4462.04 | G85: -2200.26 | H85: 10074.88 | I85: -3477.06 | J85: -5049.06 | K85: 2524.12
A90: PRICE: | B90: 30.46 | C90: 45.99 | D90: 57.11 | E90: 52.1 | F90: 26.96 | G90: 81.19 | H90: 130.72 | I90: 104.5 | J90: 155.85 | K90: 154.24
A92: DERIVED:
A93: Adjusted Equity Shares in Cr | B93: 1126.62 | C93: 1126.62 | D93: 1126.48 | E93: 1126.49 | F93: 1126.49 | G93: 1196.59 | H93: 1221.3 | I93: 1222.15 | J93: 1248.35 | K93: 1248.35
A96: market capitalisation(price value) | B96: =B93*B90 -> 34316.845 | C96: =C93*C90 -> 51813.254 | D96: =D93*D90 -> 64333.273 | E96: =E93*E90 -> 58690.129 | F96: =F93*F90 -> 30370.17 | G96: =G93*G90 -> 97151.142 | H96: =H93*H90 -> 159648.34 | I96: =I93*I90 -> 127714.68 | ... K96: =K93*K90 -> 192545.5
A97: Debt | B97: =B58 -> 81986.93 | C97: =C58 -> 83014.49 | D97: =D58 -> 92147.05 | E97: =E58 -> 100816.22 | F97: =F58 -> 116328.2 | G97: =G58 -> 88501.41 | H97: =H58 -> 75561.35 | I97: =I58 -> 84893.05 | ... K97: =K58 -> 94801.05
A98: Cash | B98: =B68 -> 6186.34 | C98: =C68 -> 4921.05 | D98: =D68 -> 7937.85 | E98: =E68 -> 3341.37 | F98: =F68 -> 8054.72 | G98: =G68 -> 5782.18 | H98: =H68 -> 15898.93 | I98: =I68 -> 13357.26 | ... K98: =K68 -> 11646.98
A99: Enterprise Value | B99: =B96+B97-B98 -> 110117.44 | C99: =C96+C97-C98 -> 129906.69 | D99: =D96+D97-D98 -> 148542.47 | E99: =E96+E97-E98 -> 156164.98 | F99: =F96+F97-F98 -> 138643.65 | G99: =G96+G97-G98 -> 179870.37 | H99: =H96+H97-H98 -> 219310.76 | I99: =I96+I97-I98 -> 199250.46 | ... K99: =K96+K97-K98 -> 275699.57
A100: EV/EBITDA | B100: =B99/B51 -> -55.47394 | C100: =C99/C51 -> 20.878741 | D100: =D99/D51 -> 23.668373 | E100: =E99/E51 -> 23.204306 | F100: =F99/F51 -> 20.367566 | G100: =G99/G51 -> 29.601178 | H100: =H99/H51 -> 32.212075 | I100: =I99/I51 -> 25.762492 | ... K100: =K99/K51 -> 31.97184
B101: =+A57:A68+'data sheet'!B48+'data sheet'!A57:A68+'data sheet'!E76 -> #VALUE!
A103: EV/Sales | B103: =B99/B17 -> 1.0799562 | C103: =C99/C17 -> 1.1567886 | D103: =D99/D17 -> 1.2052219 | E103: =E99/E17 -> 0.99046096 | F103: =F99/F17 -> 0.99161044 | G103: =G99/G17 -> 1.1494974 | H103: =H99/H17 -> 0.898965 | I103: =I99/I17 -> 0.8187724 | ... K103: =K99/K17 -> 1.2615375
A104: Book Value | B104: =B56+B57 -> 43732.55 | C104: =C56+C57 -> 37819.32 | D104: =D56+D57 -> 60870.62 | E104: =E56+E57 -> 68925.08 | F104: =F56+F57 -> 73576.3 | G104: =G56+G57 -> 74238.77 | H104: =H56+H57 -> 114443.04 | I104: =I56+I57 -> 103082.1 | ... K104: =K56+K57 -> 91169.63
A106: Price /Book value | B106: =B96/B104 -> 0.78469802 | C106: =C96/C104 -> 1.3700208 | D106: =D96/D104 -> 1.0568855 | E106: =E96/E104 -> 0.85150614 | F106: =F96/F104 -> 0.4127711 | G106: =G96/G104 -> 1.3086308 | H106: =H96/H104 -> 1.3950026 | I106: =I96/I104 -> 1.2389607 | ... K106: =K96/K104 -> 2.1119478
